{"paths": {"admin/js/vendor/select2/i18n/dsb.js": "admin/js/vendor/select2/i18n/dsb.56372c92d2f1.js", "admin/js/vendor/select2/i18n/sr.js": "admin/js/vendor/select2/i18n/sr.5ed85a48f483.js", "admin/js/vendor/select2/i18n/el.js": "admin/js/vendor/select2/i18n/el.27097f071856.js", "admin/js/vendor/select2/i18n/sq.js": "admin/js/vendor/select2/i18n/sq.5636b60d29c9.js", "admin/js/vendor/select2/i18n/sv.js": "admin/js/vendor/select2/i18n/sv.7a9c2f71e777.js", "admin/js/vendor/select2/i18n/sr-Cyrl.js": "admin/js/vendor/select2/i18n/sr-Cyrl.f254bb8c4c7c.js", "admin/js/vendor/select2/i18n/bs.js": "admin/js/vendor/select2/i18n/bs.91624382358e.js", "admin/js/vendor/select2/i18n/hr.js": "admin/js/vendor/select2/i18n/hr.a2b092cc1147.js", "admin/js/vendor/select2/i18n/bn.js": "admin/js/vendor/select2/i18n/bn.6d42b4dd5665.js", "admin/js/vendor/select2/i18n/et.js": "admin/js/vendor/select2/i18n/et.2b96fd98289d.js", "admin/js/vendor/select2/i18n/he.js": "admin/js/vendor/select2/i18n/he.e420ff6cd3ed.js", "admin/js/vendor/select2/i18n/zh-TW.js": "admin/js/vendor/select2/i18n/zh-TW.04554a227c2b.js", "admin/js/vendor/select2/i18n/de.js": "admin/js/vendor/select2/i18n/de.8a1c222b0204.js", "admin/js/vendor/select2/i18n/sk.js": "admin/js/vendor/select2/i18n/sk.33d02cef8d11.js", "admin/js/vendor/select2/i18n/en.js": "admin/js/vendor/select2/i18n/en.cf932ba09a98.js", "admin/js/vendor/select2/i18n/eu.js": "admin/js/vendor/select2/i18n/eu.adfe5c97b72c.js", "admin/js/vendor/select2/i18n/af.js": "admin/js/vendor/select2/i18n/af.4f6fcd73488c.js", "admin/js/vendor/select2/i18n/lt.js": "admin/js/vendor/select2/i18n/lt.23c7ce903300.js", "admin/js/vendor/select2/i18n/uk.js": "admin/js/vendor/select2/i18n/uk.8cede7f4803c.js", "admin/js/vendor/select2/i18n/km.js": "admin/js/vendor/select2/i18n/km.c23089cb06ca.js", "admin/js/vendor/select2/i18n/hy.js": "admin/js/vendor/select2/i18n/hy.c7babaeef5a6.js", "admin/js/vendor/select2/i18n/is.js": "admin/js/vendor/select2/i18n/is.3ddd9a6a97e9.js", "admin/js/vendor/select2/i18n/mk.js": "admin/js/vendor/select2/i18n/mk.dabbb9087130.js", "admin/js/vendor/select2/i18n/ms.js": "admin/js/vendor/select2/i18n/ms.4ba82c9a51ce.js", "admin/js/vendor/select2/i18n/nl.js": "admin/js/vendor/select2/i18n/nl.997868a37ed8.js", "admin/js/vendor/select2/i18n/ne.js": "admin/js/vendor/select2/i18n/ne.3d79fd3f08db.js", "admin/js/vendor/select2/i18n/hsb.js": "admin/js/vendor/select2/i18n/hsb.fa3b55265efe.js", "admin/js/vendor/select2/i18n/ko.js": "admin/js/vendor/select2/i18n/ko.e7be6c20e673.js", "admin/js/vendor/select2/i18n/ca.js": "admin/js/vendor/select2/i18n/ca.a166b745933a.js", "admin/js/vendor/select2/i18n/da.js": "admin/js/vendor/select2/i18n/da.766346afe4dd.js", "admin/js/vendor/select2/i18n/pt-BR.js": "admin/js/vendor/select2/i18n/pt-BR.e1b294433e7f.js", "admin/js/vendor/select2/i18n/ar.js": "admin/js/vendor/select2/i18n/ar.65aa8e36bf5d.js", "admin/js/vendor/select2/i18n/cs.js": "admin/js/vendor/select2/i18n/cs.4f43e8e7d33a.js", "admin/js/vendor/select2/i18n/ro.js": "admin/js/vendor/select2/i18n/ro.f75cb460ec3b.js", "admin/js/vendor/select2/i18n/pt.js": "admin/js/vendor/select2/i18n/pt.33b4a3b44d43.js", "admin/js/vendor/select2/i18n/tr.js": "admin/js/vendor/select2/i18n/tr.b5a0643d1545.js", "admin/js/vendor/select2/i18n/az.js": "admin/js/vendor/select2/i18n/az.270c257daf81.js", "admin/js/vendor/select2/i18n/es.js": "admin/js/vendor/select2/i18n/es.66dbc2652fb1.js", "admin/js/vendor/select2/i18n/it.js": "admin/js/vendor/select2/i18n/it.be4fe8d365b5.js", "admin/js/vendor/select2/i18n/ps.js": "admin/js/vendor/select2/i18n/ps.38dfa47af9e0.js", "admin/js/vendor/select2/i18n/tk.js": "admin/js/vendor/select2/i18n/tk.7c572a68c78f.js", "admin/js/vendor/select2/i18n/hi.js": "admin/js/vendor/select2/i18n/hi.70640d41628f.js", "admin/js/vendor/select2/i18n/lv.js": "admin/js/vendor/select2/i18n/lv.08e62128eac1.js", "admin/js/vendor/select2/i18n/id.js": "admin/js/vendor/select2/i18n/id.04debded514d.js", "admin/js/vendor/select2/i18n/bg.js": "admin/js/vendor/select2/i18n/bg.39b8be30d4f0.js", "admin/js/vendor/select2/i18n/sl.js": "admin/js/vendor/select2/i18n/sl.131a78bc0752.js", "admin/js/vendor/select2/i18n/gl.js": "admin/js/vendor/select2/i18n/gl.d99b1fedaa86.js", "admin/js/vendor/select2/i18n/fr.js": "admin/js/vendor/select2/i18n/fr.05e0542fcfe6.js", "admin/js/vendor/select2/i18n/ru.js": "admin/js/vendor/select2/i18n/ru.934aa95f5b5f.js", "admin/js/vendor/select2/i18n/hu.js": "admin/js/vendor/select2/i18n/hu.6ec6039cb8a3.js", "admin/js/vendor/select2/i18n/vi.js": "admin/js/vendor/select2/i18n/vi.097a5b75b3e1.js", "admin/js/vendor/select2/i18n/fi.js": "admin/js/vendor/select2/i18n/fi.614ec42aa9ba.js", "admin/js/vendor/select2/i18n/pl.js": "admin/js/vendor/select2/i18n/pl.6031b4f16452.js", "admin/js/vendor/select2/i18n/th.js": "admin/js/vendor/select2/i18n/th.f38c20b0221b.js", "admin/js/vendor/select2/i18n/ja.js": "admin/js/vendor/select2/i18n/ja.170ae885d74f.js", "admin/js/vendor/select2/i18n/zh-CN.js": "admin/js/vendor/select2/i18n/zh-CN.2cff662ec5f9.js", "admin/js/vendor/select2/i18n/fa.js": "admin/js/vendor/select2/i18n/fa.3b5bd1961cfd.js", "admin/js/vendor/select2/i18n/nb.js": "admin/js/vendor/select2/i18n/nb.da2fce143f27.js", "admin/js/vendor/select2/i18n/ka.js": "admin/js/vendor/select2/i18n/ka.2083264a54f0.js", "assets/vendors/flag-icon-css/flags/4x3/sc.svg": "assets/vendors/flag-icon-css/flags/4x3/sc.e6584421fdc8.svg", "assets/vendors/flag-icon-css/flags/4x3/sg.svg": "assets/vendors/flag-icon-css/flags/4x3/sg.5e6ed3f10d1d.svg", "assets/vendors/flag-icon-css/flags/4x3/ro.svg": "assets/vendors/flag-icon-css/flags/4x3/ro.625aca9e928c.svg", "assets/vendors/flag-icon-css/flags/4x3/pw.svg": "assets/vendors/flag-icon-css/flags/4x3/pw.20a1d020151e.svg", "assets/vendors/flag-icon-css/flags/4x3/af.svg": "assets/vendors/flag-icon-css/flags/4x3/af.008dc3229529.svg", "assets/vendors/flag-icon-css/flags/4x3/va.svg": "assets/vendors/flag-icon-css/flags/4x3/va.21913d789a3d.svg", "assets/vendors/flag-icon-css/flags/4x3/uy.svg": "assets/vendors/flag-icon-css/flags/4x3/uy.79b02850081e.svg", "assets/vendors/flag-icon-css/flags/4x3/cx.svg": "assets/vendors/flag-icon-css/flags/4x3/cx.aa81bb9ef6d3.svg", "assets/vendors/flag-icon-css/flags/4x3/lc.svg": "assets/vendors/flag-icon-css/flags/4x3/lc.1c3a5554a0d8.svg", "assets/vendors/flag-icon-css/flags/4x3/fj.svg": "assets/vendors/flag-icon-css/flags/4x3/fj.60620e850f30.svg", "assets/vendors/flag-icon-css/flags/4x3/ad.svg": "assets/vendors/flag-icon-css/flags/4x3/ad.d42274826fce.svg", "assets/vendors/flag-icon-css/flags/4x3/xk.svg": "assets/vendors/flag-icon-css/flags/4x3/xk.62bc9bcf96e7.svg", "assets/vendors/flag-icon-css/flags/4x3/tt.svg": "assets/vendors/flag-icon-css/flags/4x3/tt.c3647d9bc890.svg", "assets/vendors/flag-icon-css/flags/4x3/jp.svg": "assets/vendors/flag-icon-css/flags/4x3/jp.3e72015c5378.svg", "assets/vendors/flag-icon-css/flags/4x3/pe.svg": "assets/vendors/flag-icon-css/flags/4x3/pe.ea95116f76c8.svg", "assets/vendors/flag-icon-css/flags/4x3/cw.svg": "assets/vendors/flag-icon-css/flags/4x3/cw.f1b3043c88d5.svg", "assets/vendors/flag-icon-css/flags/4x3/er.svg": "assets/vendors/flag-icon-css/flags/4x3/er.e5e5e397d9e7.svg", "assets/vendors/flag-icon-css/flags/4x3/om.svg": "assets/vendors/flag-icon-css/flags/4x3/om.1798270ba5e7.svg", "assets/vendors/flag-icon-css/flags/4x3/sr.svg": "assets/vendors/flag-icon-css/flags/4x3/sr.788f3e2af54f.svg", "assets/vendors/flag-icon-css/flags/4x3/pt.svg": "assets/vendors/flag-icon-css/flags/4x3/pt.b908edaecfb2.svg", "assets/vendors/flag-icon-css/flags/4x3/by.svg": "assets/vendors/flag-icon-css/flags/4x3/by.f4cbd761094b.svg", "assets/vendors/flag-icon-css/flags/4x3/wf.svg": "assets/vendors/flag-icon-css/flags/4x3/wf.e3ac728c6286.svg", "assets/vendors/flag-icon-css/flags/4x3/vu.svg": "assets/vendors/flag-icon-css/flags/4x3/vu.859836e7f7e2.svg", "assets/vendors/flag-icon-css/flags/4x3/ly.svg": "assets/vendors/flag-icon-css/flags/4x3/ly.d089645e2ba9.svg", "assets/vendors/flag-icon-css/flags/4x3/ec.svg": "assets/vendors/flag-icon-css/flags/4x3/ec.5d6fdbf808b1.svg", "assets/vendors/flag-icon-css/flags/4x3/ag.svg": "assets/vendors/flag-icon-css/flags/4x3/ag.cce32c739dde.svg", "assets/vendors/flag-icon-css/flags/4x3/pr.svg": "assets/vendors/flag-icon-css/flags/4x3/pr.0811a0517cf3.svg", "assets/vendors/flag-icon-css/flags/4x3/tr.svg": "assets/vendors/flag-icon-css/flags/4x3/tr.ed6d5f37779a.svg", "assets/vendors/flag-icon-css/flags/4x3/eh.svg": "assets/vendors/flag-icon-css/flags/4x3/eh.3b662831ee7d.svg", "assets/vendors/flag-icon-css/flags/4x3/mm.svg": "assets/vendors/flag-icon-css/flags/4x3/mm.92e9f832a28f.svg", "assets/vendors/flag-icon-css/flags/4x3/gn.svg": "assets/vendors/flag-icon-css/flags/4x3/gn.36a3e9a3dd82.svg", "assets/vendors/flag-icon-css/flags/4x3/gb-eng.svg": "assets/vendors/flag-icon-css/flags/4x3/gb-eng.14167f77f128.svg", "assets/vendors/flag-icon-css/flags/4x3/bh.svg": "assets/vendors/flag-icon-css/flags/4x3/bh.ef135f3ca778.svg", "assets/vendors/flag-icon-css/flags/4x3/pl.svg": "assets/vendors/flag-icon-css/flags/4x3/pl.562edca5bb39.svg", "assets/vendors/flag-icon-css/flags/4x3/us.svg": "assets/vendors/flag-icon-css/flags/4x3/us.ae65659236a7.svg", "assets/vendors/flag-icon-css/flags/4x3/sx.svg": "assets/vendors/flag-icon-css/flags/4x3/sx.522d898c1939.svg", "assets/vendors/flag-icon-css/flags/4x3/km.svg": "assets/vendors/flag-icon-css/flags/4x3/km.9b06043d7f9a.svg", "assets/vendors/flag-icon-css/flags/4x3/mc.svg": "assets/vendors/flag-icon-css/flags/4x3/mc.b4f4b90da301.svg", "assets/vendors/flag-icon-css/flags/4x3/lr.svg": "assets/vendors/flag-icon-css/flags/4x3/lr.309ccbd814f8.svg", "assets/vendors/flag-icon-css/flags/4x3/gf.svg": "assets/vendors/flag-icon-css/flags/4x3/gf.38dfa23a36e1.svg", "assets/vendors/flag-icon-css/flags/4x3/ck.svg": "assets/vendors/flag-icon-css/flags/4x3/ck.960a7b5a2c23.svg", "assets/vendors/flag-icon-css/flags/4x3/ru.svg": "assets/vendors/flag-icon-css/flags/4x3/ru.0cacf46e6f47.svg", "assets/vendors/flag-icon-css/flags/4x3/sh.svg": "assets/vendors/flag-icon-css/flags/4x3/sh.6560d76bf100.svg", "assets/vendors/flag-icon-css/flags/4x3/cz.svg": "assets/vendors/flag-icon-css/flags/4x3/cz.c1ef59925bf1.svg", "assets/vendors/flag-icon-css/flags/4x3/np.svg": "assets/vendors/flag-icon-css/flags/4x3/np.b66578a5c732.svg", "assets/vendors/flag-icon-css/flags/4x3/au.svg": "assets/vendors/flag-icon-css/flags/4x3/au.503a3a980ccb.svg", "assets/vendors/flag-icon-css/flags/4x3/gg.svg": "assets/vendors/flag-icon-css/flags/4x3/gg.98f67a6ff36a.svg", "assets/vendors/flag-icon-css/flags/4x3/cr.svg": "assets/vendors/flag-icon-css/flags/4x3/cr.7b4ebd50f527.svg", "assets/vendors/flag-icon-css/flags/4x3/ua.svg": "assets/vendors/flag-icon-css/flags/4x3/ua.a8b13525ee3b.svg", "assets/vendors/flag-icon-css/flags/4x3/mh.svg": "assets/vendors/flag-icon-css/flags/4x3/mh.6d60cee3ee8d.svg", "assets/vendors/flag-icon-css/flags/4x3/ai.svg": "assets/vendors/flag-icon-css/flags/4x3/ai.c2f29c4d57cf.svg", "assets/vendors/flag-icon-css/flags/4x3/mz.svg": "assets/vendors/flag-icon-css/flags/4x3/mz.ef4657da4e39.svg", "assets/vendors/flag-icon-css/flags/4x3/bb.svg": "assets/vendors/flag-icon-css/flags/4x3/bb.9873885f352c.svg", "assets/vendors/flag-icon-css/flags/4x3/jm.svg": "assets/vendors/flag-icon-css/flags/4x3/jm.67f96b2f0df3.svg", "assets/vendors/flag-icon-css/flags/4x3/lv.svg": "assets/vendors/flag-icon-css/flags/4x3/lv.8b293d984cea.svg", "assets/vendors/flag-icon-css/flags/4x3/fk.svg": "assets/vendors/flag-icon-css/flags/4x3/fk.519e3de544b4.svg", "assets/vendors/flag-icon-css/flags/4x3/dj.svg": "assets/vendors/flag-icon-css/flags/4x3/dj.423c41561146.svg", "assets/vendors/flag-icon-css/flags/4x3/um.svg": "assets/vendors/flag-icon-css/flags/4x3/um.8754eddfe66c.svg", "assets/vendors/flag-icon-css/flags/4x3/kg.svg": "assets/vendors/flag-icon-css/flags/4x3/kg.1cfa1c79dd52.svg", "assets/vendors/flag-icon-css/flags/4x3/mp.svg": "assets/vendors/flag-icon-css/flags/4x3/mp.c5eb7f233b09.svg", "assets/vendors/flag-icon-css/flags/4x3/ky.svg": "assets/vendors/flag-icon-css/flags/4x3/ky.5814c5a94343.svg", "assets/vendors/flag-icon-css/flags/4x3/ht.svg": "assets/vendors/flag-icon-css/flags/4x3/ht.fb289ca05aec.svg", "assets/vendors/flag-icon-css/flags/4x3/ss.svg": "assets/vendors/flag-icon-css/flags/4x3/ss.67001d2a8840.svg", "assets/vendors/flag-icon-css/flags/4x3/mx.svg": "assets/vendors/flag-icon-css/flags/4x3/mx.8ee3aa6a7fea.svg", "assets/vendors/flag-icon-css/flags/4x3/it.svg": "assets/vendors/flag-icon-css/flags/4x3/it.8d15de04f5f6.svg", "assets/vendors/flag-icon-css/flags/4x3/je.svg": "assets/vendors/flag-icon-css/flags/4x3/je.62999e4b073e.svg", "assets/vendors/flag-icon-css/flags/4x3/qa.svg": "assets/vendors/flag-icon-css/flags/4x3/qa.b314986b75f2.svg", "assets/vendors/flag-icon-css/flags/4x3/do.svg": "assets/vendors/flag-icon-css/flags/4x3/do.79f8bf8c1a68.svg", "assets/vendors/flag-icon-css/flags/4x3/mq.svg": "assets/vendors/flag-icon-css/flags/4x3/mq.bfeadb02a0e0.svg", "assets/vendors/flag-icon-css/flags/4x3/ws.svg": "assets/vendors/flag-icon-css/flags/4x3/ws.405a2c5f0363.svg", "assets/vendors/flag-icon-css/flags/4x3/at.svg": "assets/vendors/flag-icon-css/flags/4x3/at.e2634e96c9ad.svg", "assets/vendors/flag-icon-css/flags/4x3/il.svg": "assets/vendors/flag-icon-css/flags/4x3/il.874270d66e95.svg", "assets/vendors/flag-icon-css/flags/4x3/sz.svg": "assets/vendors/flag-icon-css/flags/4x3/sz.cfb8269f38d5.svg", "assets/vendors/flag-icon-css/flags/4x3/tf.svg": "assets/vendors/flag-icon-css/flags/4x3/tf.4ab43cc9db28.svg", "assets/vendors/flag-icon-css/flags/4x3/mv.svg": "assets/vendors/flag-icon-css/flags/4x3/mv.3c896bfdad2f.svg", "assets/vendors/flag-icon-css/flags/4x3/gb-wls.svg": "assets/vendors/flag-icon-css/flags/4x3/gb-wls.2d554424b763.svg", "assets/vendors/flag-icon-css/flags/4x3/lu.svg": "assets/vendors/flag-icon-css/flags/4x3/lu.c858787cf95b.svg", "assets/vendors/flag-icon-css/flags/4x3/gr.svg": "assets/vendors/flag-icon-css/flags/4x3/gr.471d733ad436.svg", "assets/vendors/flag-icon-css/flags/4x3/ge.svg": "assets/vendors/flag-icon-css/flags/4x3/ge.16f859b527e5.svg", "assets/vendors/flag-icon-css/flags/4x3/sa.svg": "assets/vendors/flag-icon-css/flags/4x3/sa.c36d1991b52c.svg", "assets/vendors/flag-icon-css/flags/4x3/kp.svg": "assets/vendors/flag-icon-css/flags/4x3/kp.9c53429167b9.svg", "assets/vendors/flag-icon-css/flags/4x3/zm.svg": "assets/vendors/flag-icon-css/flags/4x3/zm.a9ff495dd331.svg", "assets/vendors/flag-icon-css/flags/4x3/gm.svg": "assets/vendors/flag-icon-css/flags/4x3/gm.50fe2799b099.svg", "assets/vendors/flag-icon-css/flags/4x3/bf.svg": "assets/vendors/flag-icon-css/flags/4x3/bf.9a958401fd12.svg", "assets/vendors/flag-icon-css/flags/4x3/th.svg": "assets/vendors/flag-icon-css/flags/4x3/th.76fca72f6d18.svg", "assets/vendors/flag-icon-css/flags/4x3/bo.svg": "assets/vendors/flag-icon-css/flags/4x3/bo.4128202a176b.svg", "assets/vendors/flag-icon-css/flags/4x3/cd.svg": "assets/vendors/flag-icon-css/flags/4x3/cd.cd346cdc7caa.svg", "assets/vendors/flag-icon-css/flags/4x3/et.svg": "assets/vendors/flag-icon-css/flags/4x3/et.2ebb0d3d6e63.svg", "assets/vendors/flag-icon-css/flags/4x3/gs.svg": "assets/vendors/flag-icon-css/flags/4x3/gs.0ee2d8c9dbe3.svg", "assets/vendors/flag-icon-css/flags/4x3/io.svg": "assets/vendors/flag-icon-css/flags/4x3/io.3ddd1280f6e3.svg", "assets/vendors/flag-icon-css/flags/4x3/ga.svg": "assets/vendors/flag-icon-css/flags/4x3/ga.29f203bb2828.svg", "assets/vendors/flag-icon-css/flags/4x3/bz.svg": "assets/vendors/flag-icon-css/flags/4x3/bz.64d617eaf3f2.svg", "assets/vendors/flag-icon-css/flags/4x3/tz.svg": "assets/vendors/flag-icon-css/flags/4x3/tz.88c89454adfe.svg", "assets/vendors/flag-icon-css/flags/4x3/es-ca.svg": "assets/vendors/flag-icon-css/flags/4x3/es-ca.e9062265c973.svg", "assets/vendors/flag-icon-css/flags/4x3/cu.svg": "assets/vendors/flag-icon-css/flags/4x3/cu.750c91b200d2.svg", "assets/vendors/flag-icon-css/flags/4x3/fo.svg": "assets/vendors/flag-icon-css/flags/4x3/fo.037e466d03f8.svg", "assets/vendors/flag-icon-css/flags/4x3/pn.svg": "assets/vendors/flag-icon-css/flags/4x3/pn.c4a2e49ffb6e.svg", "assets/vendors/flag-icon-css/flags/4x3/hk.svg": "assets/vendors/flag-icon-css/flags/4x3/hk.7428ec1c4806.svg", "assets/vendors/flag-icon-css/flags/4x3/ca.svg": "assets/vendors/flag-icon-css/flags/4x3/ca.c976442e32a4.svg", "assets/vendors/flag-icon-css/flags/4x3/ms.svg": "assets/vendors/flag-icon-css/flags/4x3/ms.e147bd2bb2aa.svg", "assets/vendors/flag-icon-css/flags/4x3/iq.svg": "assets/vendors/flag-icon-css/flags/4x3/iq.be9919971db8.svg", "assets/vendors/flag-icon-css/flags/4x3/gw.svg": "assets/vendors/flag-icon-css/flags/4x3/gw.c1e88a916be1.svg", "assets/vendors/flag-icon-css/flags/4x3/na.svg": "assets/vendors/flag-icon-css/flags/4x3/na.bb49a4035c38.svg", "assets/vendors/flag-icon-css/flags/4x3/bd.svg": "assets/vendors/flag-icon-css/flags/4x3/bd.5102bab03db6.svg", "assets/vendors/flag-icon-css/flags/4x3/gi.svg": "assets/vendors/flag-icon-css/flags/4x3/gi.dce455a731d7.svg", "assets/vendors/flag-icon-css/flags/4x3/ee.svg": "assets/vendors/flag-icon-css/flags/4x3/ee.6088c9ceb092.svg", "assets/vendors/flag-icon-css/flags/4x3/re.svg": "assets/vendors/flag-icon-css/flags/4x3/re.17909e3784b7.svg", "assets/vendors/flag-icon-css/flags/4x3/ve.svg": "assets/vendors/flag-icon-css/flags/4x3/ve.b2cd5a9a011f.svg", "assets/vendors/flag-icon-css/flags/4x3/co.svg": "assets/vendors/flag-icon-css/flags/4x3/co.3b252a1a9126.svg", "assets/vendors/flag-icon-css/flags/4x3/mr.svg": "assets/vendors/flag-icon-css/flags/4x3/mr.a46829f17f8f.svg", "assets/vendors/flag-icon-css/flags/4x3/sl.svg": "assets/vendors/flag-icon-css/flags/4x3/sl.ddbd1d9b113b.svg", "assets/vendors/flag-icon-css/flags/4x3/kr.svg": "assets/vendors/flag-icon-css/flags/4x3/kr.60fde7fc2f60.svg", "assets/vendors/flag-icon-css/flags/4x3/za.svg": "assets/vendors/flag-icon-css/flags/4x3/za.14e7052257d9.svg", "assets/vendors/flag-icon-css/flags/4x3/la.svg": "assets/vendors/flag-icon-css/flags/4x3/la.0f124ae33af5.svg", "assets/vendors/flag-icon-css/flags/4x3/vi.svg": "assets/vendors/flag-icon-css/flags/4x3/vi.4952d5bf33f7.svg", "assets/vendors/flag-icon-css/flags/4x3/de.svg": "assets/vendors/flag-icon-css/flags/4x3/de.3e726c2b6a59.svg", "assets/vendors/flag-icon-css/flags/4x3/gu.svg": "assets/vendors/flag-icon-css/flags/4x3/gu.2284e60e378b.svg", "assets/vendors/flag-icon-css/flags/4x3/nr.svg": "assets/vendors/flag-icon-css/flags/4x3/nr.d16edc69065b.svg", "assets/vendors/flag-icon-css/flags/4x3/am.svg": "assets/vendors/flag-icon-css/flags/4x3/am.06509258e611.svg", "assets/vendors/flag-icon-css/flags/4x3/hr.svg": "assets/vendors/flag-icon-css/flags/4x3/hr.4680d6323b39.svg", "assets/vendors/flag-icon-css/flags/4x3/ps.svg": "assets/vendors/flag-icon-css/flags/4x3/ps.42f2391e39ad.svg", "assets/vendors/flag-icon-css/flags/4x3/nf.svg": "assets/vendors/flag-icon-css/flags/4x3/nf.99af5a94b011.svg", "assets/vendors/flag-icon-css/flags/4x3/lb.svg": "assets/vendors/flag-icon-css/flags/4x3/lb.e33a49a9a071.svg", "assets/vendors/flag-icon-css/flags/4x3/gl.svg": "assets/vendors/flag-icon-css/flags/4x3/gl.2490aa08f408.svg", "assets/vendors/flag-icon-css/flags/4x3/cm.svg": "assets/vendors/flag-icon-css/flags/4x3/cm.5799ad4c126b.svg", "assets/vendors/flag-icon-css/flags/4x3/ae.svg": "assets/vendors/flag-icon-css/flags/4x3/ae.9fd1fcbfedb5.svg", "assets/vendors/flag-icon-css/flags/4x3/ci.svg": "assets/vendors/flag-icon-css/flags/4x3/ci.d939dcac6117.svg", "assets/vendors/flag-icon-css/flags/4x3/mg.svg": "assets/vendors/flag-icon-css/flags/4x3/mg.67f5922d7885.svg", "assets/vendors/flag-icon-css/flags/4x3/tw.svg": "assets/vendors/flag-icon-css/flags/4x3/tw.8a1946853789.svg", "assets/vendors/flag-icon-css/flags/4x3/br.svg": "assets/vendors/flag-icon-css/flags/4x3/br.87032851c353.svg", "assets/vendors/flag-icon-css/flags/4x3/dm.svg": "assets/vendors/flag-icon-css/flags/4x3/dm.46f58d408f6a.svg", "assets/vendors/flag-icon-css/flags/4x3/pk.svg": "assets/vendors/flag-icon-css/flags/4x3/pk.c2e1a15939a2.svg", "assets/vendors/flag-icon-css/flags/4x3/bm.svg": "assets/vendors/flag-icon-css/flags/4x3/bm.0fdefae88aae.svg", "assets/vendors/flag-icon-css/flags/4x3/bj.svg": "assets/vendors/flag-icon-css/flags/4x3/bj.c81e89154350.svg", "assets/vendors/flag-icon-css/flags/4x3/ki.svg": "assets/vendors/flag-icon-css/flags/4x3/ki.db7e40f60e21.svg", "assets/vendors/flag-icon-css/flags/4x3/yt.svg": "assets/vendors/flag-icon-css/flags/4x3/yt.f06d254d5978.svg", "assets/vendors/flag-icon-css/flags/4x3/fm.svg": "assets/vendors/flag-icon-css/flags/4x3/fm.59c5190c55c6.svg", "assets/vendors/flag-icon-css/flags/4x3/dz.svg": "assets/vendors/flag-icon-css/flags/4x3/dz.4be984a3b7c8.svg", "assets/vendors/flag-icon-css/flags/4x3/ni.svg": "assets/vendors/flag-icon-css/flags/4x3/ni.7b131ab3ceaf.svg", "assets/vendors/flag-icon-css/flags/4x3/pa.svg": "assets/vendors/flag-icon-css/flags/4x3/pa.d0787677f0d7.svg", "assets/vendors/flag-icon-css/flags/4x3/mu.svg": "assets/vendors/flag-icon-css/flags/4x3/mu.896330b72092.svg", "assets/vendors/flag-icon-css/flags/4x3/gt.svg": "assets/vendors/flag-icon-css/flags/4x3/gt.656c9899d22b.svg", "assets/vendors/flag-icon-css/flags/4x3/vg.svg": "assets/vendors/flag-icon-css/flags/4x3/vg.b37358a1a76a.svg", "assets/vendors/flag-icon-css/flags/4x3/kw.svg": "assets/vendors/flag-icon-css/flags/4x3/kw.496fa4662f48.svg", "assets/vendors/flag-icon-css/flags/4x3/gq.svg": "assets/vendors/flag-icon-css/flags/4x3/gq.30ed019c10e7.svg", "assets/vendors/flag-icon-css/flags/4x3/tj.svg": "assets/vendors/flag-icon-css/flags/4x3/tj.a8ed5244d61d.svg", "assets/vendors/flag-icon-css/flags/4x3/ir.svg": "assets/vendors/flag-icon-css/flags/4x3/ir.23e0f96c3fa4.svg", "assets/vendors/flag-icon-css/flags/4x3/kh.svg": "assets/vendors/flag-icon-css/flags/4x3/kh.5a13865d2bca.svg", "assets/vendors/flag-icon-css/flags/4x3/to.svg": "assets/vendors/flag-icon-css/flags/4x3/to.79354e72ad05.svg", "assets/vendors/flag-icon-css/flags/4x3/eg.svg": "assets/vendors/flag-icon-css/flags/4x3/eg.6b83ab95bd23.svg", "assets/vendors/flag-icon-css/flags/4x3/be.svg": "assets/vendors/flag-icon-css/flags/4x3/be.27d8ca49197f.svg", "assets/vendors/flag-icon-css/flags/4x3/tg.svg": "assets/vendors/flag-icon-css/flags/4x3/tg.025deae88a72.svg", "assets/vendors/flag-icon-css/flags/4x3/so.svg": "assets/vendors/flag-icon-css/flags/4x3/so.f91fb92c0ca6.svg", "assets/vendors/flag-icon-css/flags/4x3/mt.svg": "assets/vendors/flag-icon-css/flags/4x3/mt.a816f3a2978c.svg", "assets/vendors/flag-icon-css/flags/4x3/bs.svg": "assets/vendors/flag-icon-css/flags/4x3/bs.9f8a4eae81ab.svg", "assets/vendors/flag-icon-css/flags/4x3/pm.svg": "assets/vendors/flag-icon-css/flags/4x3/pm.1e97e8d76fe2.svg", "assets/vendors/flag-icon-css/flags/4x3/nu.svg": "assets/vendors/flag-icon-css/flags/4x3/nu.433deb3d047d.svg", "assets/vendors/flag-icon-css/flags/4x3/hn.svg": "assets/vendors/flag-icon-css/flags/4x3/hn.9b9bee13c67a.svg", "assets/vendors/flag-icon-css/flags/4x3/ne.svg": "assets/vendors/flag-icon-css/flags/4x3/ne.b7369ec74cd2.svg", "assets/vendors/flag-icon-css/flags/4x3/pf.svg": "assets/vendors/flag-icon-css/flags/4x3/pf.bab3b7a56aa5.svg", "assets/vendors/flag-icon-css/flags/4x3/bn.svg": "assets/vendors/flag-icon-css/flags/4x3/bn.1d4e60918c47.svg", "assets/vendors/flag-icon-css/flags/4x3/sj.svg": "assets/vendors/flag-icon-css/flags/4x3/sj.ae547dbec390.svg", "assets/vendors/flag-icon-css/flags/4x3/sk.svg": "assets/vendors/flag-icon-css/flags/4x3/sk.b84444bf8d98.svg", "assets/vendors/flag-icon-css/flags/4x3/st.svg": "assets/vendors/flag-icon-css/flags/4x3/st.1f545eb99b32.svg", "assets/vendors/flag-icon-css/flags/4x3/ml.svg": "assets/vendors/flag-icon-css/flags/4x3/ml.e6f097f93a69.svg", "assets/vendors/flag-icon-css/flags/4x3/hm.svg": "assets/vendors/flag-icon-css/flags/4x3/hm.fe514431ce79.svg", "assets/vendors/flag-icon-css/flags/4x3/vc.svg": "assets/vendors/flag-icon-css/flags/4x3/vc.4ac5124fbf60.svg", "assets/vendors/flag-icon-css/flags/4x3/mf.svg": "assets/vendors/flag-icon-css/flags/4x3/mf.5b9ff36c7fed.svg", "assets/vendors/flag-icon-css/flags/4x3/cg.svg": "assets/vendors/flag-icon-css/flags/4x3/cg.4396b867b33a.svg", "assets/vendors/flag-icon-css/flags/4x3/cf.svg": "assets/vendors/flag-icon-css/flags/4x3/cf.2171101e459d.svg", "assets/vendors/flag-icon-css/flags/4x3/hu.svg": "assets/vendors/flag-icon-css/flags/4x3/hu.0d7409f88bca.svg", "assets/vendors/flag-icon-css/flags/4x3/ch.svg": "assets/vendors/flag-icon-css/flags/4x3/ch.9c26f60a63bf.svg", "assets/vendors/flag-icon-css/flags/4x3/mk.svg": "assets/vendors/flag-icon-css/flags/4x3/mk.ed091b887caf.svg", "assets/vendors/flag-icon-css/flags/4x3/mo.svg": "assets/vendors/flag-icon-css/flags/4x3/mo.e1178856d7fe.svg", "assets/vendors/flag-icon-css/flags/4x3/me.svg": "assets/vendors/flag-icon-css/flags/4x3/me.76c434a613ae.svg", "assets/vendors/flag-icon-css/flags/4x3/ug.svg": "assets/vendors/flag-icon-css/flags/4x3/ug.be11ef3932f4.svg", "assets/vendors/flag-icon-css/flags/4x3/cy.svg": "assets/vendors/flag-icon-css/flags/4x3/cy.d069616cbc4f.svg", "assets/vendors/flag-icon-css/flags/4x3/tn.svg": "assets/vendors/flag-icon-css/flags/4x3/tn.50cd91018d74.svg", "assets/vendors/flag-icon-css/flags/4x3/is.svg": "assets/vendors/flag-icon-css/flags/4x3/is.2ce20c50765b.svg", "assets/vendors/flag-icon-css/flags/4x3/gh.svg": "assets/vendors/flag-icon-css/flags/4x3/gh.caedb9129bf6.svg", "assets/vendors/flag-icon-css/flags/4x3/se.svg": "assets/vendors/flag-icon-css/flags/4x3/se.ee9cde492630.svg", "assets/vendors/flag-icon-css/flags/4x3/gb-nir.svg": "assets/vendors/flag-icon-css/flags/4x3/gb-nir.43b61feaa71f.svg", "assets/vendors/flag-icon-css/flags/4x3/aq.svg": "assets/vendors/flag-icon-css/flags/4x3/aq.65afe1f1ffb9.svg", "assets/vendors/flag-icon-css/flags/4x3/nl.svg": "assets/vendors/flag-icon-css/flags/4x3/nl.d4811c278d65.svg", "assets/vendors/flag-icon-css/flags/4x3/ao.svg": "assets/vendors/flag-icon-css/flags/4x3/ao.8b6f2ec29629.svg", "assets/vendors/flag-icon-css/flags/4x3/im.svg": "assets/vendors/flag-icon-css/flags/4x3/im.8c10222d11a2.svg", "assets/vendors/flag-icon-css/flags/4x3/ke.svg": "assets/vendors/flag-icon-css/flags/4x3/ke.dd8a91b81960.svg", "assets/vendors/flag-icon-css/flags/4x3/bq.svg": "assets/vendors/flag-icon-css/flags/4x3/bq.b551016fbdf6.svg", "assets/vendors/flag-icon-css/flags/4x3/si.svg": "assets/vendors/flag-icon-css/flags/4x3/si.31fbdc5b5842.svg", "assets/vendors/flag-icon-css/flags/4x3/gb.svg": "assets/vendors/flag-icon-css/flags/4x3/gb.d3ddd6025a06.svg", "assets/vendors/flag-icon-css/flags/4x3/ar.svg": "assets/vendors/flag-icon-css/flags/4x3/ar.d205ca1376db.svg", "assets/vendors/flag-icon-css/flags/4x3/lt.svg": "assets/vendors/flag-icon-css/flags/4x3/lt.c3aeac0dad1d.svg", "assets/vendors/flag-icon-css/flags/4x3/lk.svg": "assets/vendors/flag-icon-css/flags/4x3/lk.497ee5b9544f.svg", "assets/vendors/flag-icon-css/flags/4x3/pg.svg": "assets/vendors/flag-icon-css/flags/4x3/pg.68e1ce3359df.svg", "assets/vendors/flag-icon-css/flags/4x3/aw.svg": "assets/vendors/flag-icon-css/flags/4x3/aw.47ea7038c8fe.svg", "assets/vendors/flag-icon-css/flags/4x3/tk.svg": "assets/vendors/flag-icon-css/flags/4x3/tk.1959d9de338f.svg", "assets/vendors/flag-icon-css/flags/4x3/dk.svg": "assets/vendors/flag-icon-css/flags/4x3/dk.eb1416e02bae.svg", "assets/vendors/flag-icon-css/flags/4x3/cl.svg": "assets/vendors/flag-icon-css/flags/4x3/cl.8949f9e6d4f8.svg", "assets/vendors/flag-icon-css/flags/4x3/gy.svg": "assets/vendors/flag-icon-css/flags/4x3/gy.79fcf270400e.svg", "assets/vendors/flag-icon-css/flags/4x3/sy.svg": "assets/vendors/flag-icon-css/flags/4x3/sy.64f0d2d7a590.svg", "assets/vendors/flag-icon-css/flags/4x3/bg.svg": "assets/vendors/flag-icon-css/flags/4x3/bg.3d762564b2be.svg", "assets/vendors/flag-icon-css/flags/4x3/vn.svg": "assets/vendors/flag-icon-css/flags/4x3/vn.6b3aef51e8b5.svg", "assets/vendors/flag-icon-css/flags/4x3/mw.svg": "assets/vendors/flag-icon-css/flags/4x3/mw.6073ddcffcc7.svg", "assets/vendors/flag-icon-css/flags/4x3/eu.svg": "assets/vendors/flag-icon-css/flags/4x3/eu.ee7f4712ac45.svg", "assets/vendors/flag-icon-css/flags/4x3/bi.svg": "assets/vendors/flag-icon-css/flags/4x3/bi.06f36479b444.svg", "assets/vendors/flag-icon-css/flags/4x3/my.svg": "assets/vendors/flag-icon-css/flags/4x3/my.e6739f404c96.svg", "assets/vendors/flag-icon-css/flags/4x3/kz.svg": "assets/vendors/flag-icon-css/flags/4x3/kz.740ef4bf1d15.svg", "assets/vendors/flag-icon-css/flags/4x3/bw.svg": "assets/vendors/flag-icon-css/flags/4x3/bw.d1585fdf351c.svg", "assets/vendors/flag-icon-css/flags/4x3/bt.svg": "assets/vendors/flag-icon-css/flags/4x3/bt.65b20c56edb0.svg", "assets/vendors/flag-icon-css/flags/4x3/mn.svg": "assets/vendors/flag-icon-css/flags/4x3/mn.9ebe47ebe892.svg", "assets/vendors/flag-icon-css/flags/4x3/uz.svg": "assets/vendors/flag-icon-css/flags/4x3/uz.eb1e00b870d7.svg", "assets/vendors/flag-icon-css/flags/4x3/nz.svg": "assets/vendors/flag-icon-css/flags/4x3/nz.3241e92770d4.svg", "assets/vendors/flag-icon-css/flags/4x3/az.svg": "assets/vendors/flag-icon-css/flags/4x3/az.451284cedf72.svg", "assets/vendors/flag-icon-css/flags/4x3/jo.svg": "assets/vendors/flag-icon-css/flags/4x3/jo.9e2f2b3ac578.svg", "assets/vendors/flag-icon-css/flags/4x3/ba.svg": "assets/vendors/flag-icon-css/flags/4x3/ba.3223166179b0.svg", "assets/vendors/flag-icon-css/flags/4x3/md.svg": "assets/vendors/flag-icon-css/flags/4x3/md.5f734d921b0b.svg", "assets/vendors/flag-icon-css/flags/4x3/ls.svg": "assets/vendors/flag-icon-css/flags/4x3/ls.c0799ebf1d58.svg", "assets/vendors/flag-icon-css/flags/4x3/tv.svg": "assets/vendors/flag-icon-css/flags/4x3/tv.829fb9d89912.svg", "assets/vendors/flag-icon-css/flags/4x3/al.svg": "assets/vendors/flag-icon-css/flags/4x3/al.4eb491e7412f.svg", "assets/vendors/flag-icon-css/flags/4x3/bv.svg": "assets/vendors/flag-icon-css/flags/4x3/bv.78bef9106e11.svg", "assets/vendors/flag-icon-css/flags/4x3/es.svg": "assets/vendors/flag-icon-css/flags/4x3/es.50623e6a761b.svg", "assets/vendors/flag-icon-css/flags/4x3/ax.svg": "assets/vendors/flag-icon-css/flags/4x3/ax.c26f83744d3d.svg", "assets/vendors/flag-icon-css/flags/4x3/as.svg": "assets/vendors/flag-icon-css/flags/4x3/as.16f433a627bc.svg", "assets/vendors/flag-icon-css/flags/4x3/tl.svg": "assets/vendors/flag-icon-css/flags/4x3/tl.3c1ccf1158d7.svg", "assets/vendors/flag-icon-css/flags/4x3/sd.svg": "assets/vendors/flag-icon-css/flags/4x3/sd.c466d90ea717.svg", "assets/vendors/flag-icon-css/flags/4x3/li.svg": "assets/vendors/flag-icon-css/flags/4x3/li.fb5437d371f4.svg", "assets/vendors/flag-icon-css/flags/4x3/nc.svg": "assets/vendors/flag-icon-css/flags/4x3/nc.b8c9f5e4fa65.svg", "assets/vendors/flag-icon-css/flags/4x3/gd.svg": "assets/vendors/flag-icon-css/flags/4x3/gd.8e690a5aa1fb.svg", "assets/vendors/flag-icon-css/flags/4x3/zw.svg": "assets/vendors/flag-icon-css/flags/4x3/zw.6ac3949a90f1.svg", "assets/vendors/flag-icon-css/flags/4x3/ma.svg": "assets/vendors/flag-icon-css/flags/4x3/ma.60fbc221d84d.svg", "assets/vendors/flag-icon-css/flags/4x3/tm.svg": "assets/vendors/flag-icon-css/flags/4x3/tm.b13d1440e1d8.svg", "assets/vendors/flag-icon-css/flags/4x3/fr.svg": "assets/vendors/flag-icon-css/flags/4x3/fr.b1156355de96.svg", "assets/vendors/flag-icon-css/flags/4x3/rw.svg": "assets/vendors/flag-icon-css/flags/4x3/rw.7fe5146baf52.svg", "assets/vendors/flag-icon-css/flags/4x3/ie.svg": "assets/vendors/flag-icon-css/flags/4x3/ie.c68ff961baf0.svg", "assets/vendors/flag-icon-css/flags/4x3/no.svg": "assets/vendors/flag-icon-css/flags/4x3/no.0b41df77e951.svg", "assets/vendors/flag-icon-css/flags/4x3/id.svg": "assets/vendors/flag-icon-css/flags/4x3/id.17b996767ee0.svg", "assets/vendors/flag-icon-css/flags/4x3/cv.svg": "assets/vendors/flag-icon-css/flags/4x3/cv.f9922e019e92.svg", "assets/vendors/flag-icon-css/flags/4x3/fi.svg": "assets/vendors/flag-icon-css/flags/4x3/fi.2649533e1d44.svg", "assets/vendors/flag-icon-css/flags/4x3/gp.svg": "assets/vendors/flag-icon-css/flags/4x3/gp.fa4cab3e4ee1.svg", "assets/vendors/flag-icon-css/flags/4x3/sm.svg": "assets/vendors/flag-icon-css/flags/4x3/sm.3b1c9fb5c651.svg", "assets/vendors/flag-icon-css/flags/4x3/cc.svg": "assets/vendors/flag-icon-css/flags/4x3/cc.2da4bb974f77.svg", "assets/vendors/flag-icon-css/flags/4x3/ng.svg": "assets/vendors/flag-icon-css/flags/4x3/ng.992459a3d0f2.svg", "assets/vendors/flag-icon-css/flags/4x3/in.svg": "assets/vendors/flag-icon-css/flags/4x3/in.e4ab7bd057c6.svg", "assets/vendors/flag-icon-css/flags/4x3/sn.svg": "assets/vendors/flag-icon-css/flags/4x3/sn.5b654e1a7246.svg", "assets/vendors/flag-icon-css/flags/4x3/kn.svg": "assets/vendors/flag-icon-css/flags/4x3/kn.bde74c6da4f2.svg", "assets/vendors/flag-icon-css/flags/4x3/ye.svg": "assets/vendors/flag-icon-css/flags/4x3/ye.b5840a84dc1f.svg", "assets/vendors/flag-icon-css/flags/4x3/sv.svg": "assets/vendors/flag-icon-css/flags/4x3/sv.1176ea281282.svg", "assets/vendors/flag-icon-css/flags/4x3/py.svg": "assets/vendors/flag-icon-css/flags/4x3/py.bbc22e414bad.svg", "assets/vendors/flag-icon-css/flags/4x3/ph.svg": "assets/vendors/flag-icon-css/flags/4x3/ph.12f36eed83fd.svg", "assets/vendors/flag-icon-css/flags/4x3/tc.svg": "assets/vendors/flag-icon-css/flags/4x3/tc.d40761f21eeb.svg", "assets/vendors/flag-icon-css/flags/4x3/sb.svg": "assets/vendors/flag-icon-css/flags/4x3/sb.aa819297c44f.svg", "assets/vendors/flag-icon-css/flags/4x3/gb-sct.svg": "assets/vendors/flag-icon-css/flags/4x3/gb-sct.4c2c379f607f.svg", "assets/vendors/flag-icon-css/flags/4x3/un.svg": "assets/vendors/flag-icon-css/flags/4x3/un.bdaf37f920eb.svg", "assets/vendors/flag-icon-css/flags/4x3/bl.svg": "assets/vendors/flag-icon-css/flags/4x3/bl.38e27b684c0a.svg", "assets/vendors/flag-icon-css/flags/4x3/cn.svg": "assets/vendors/flag-icon-css/flags/4x3/cn.02c229de4d98.svg", "assets/vendors/flag-icon-css/flags/4x3/rs.svg": "assets/vendors/flag-icon-css/flags/4x3/rs.291d0fb654f2.svg", "assets/vendors/flag-icon-css/flags/4x3/td.svg": "assets/vendors/flag-icon-css/flags/4x3/td.a0923ddc3c8a.svg", "assets/vendors/flag-icon-css/flags/1x1/sc.svg": "assets/vendors/flag-icon-css/flags/1x1/sc.ad1bcb4c714e.svg", "assets/vendors/flag-icon-css/flags/1x1/sg.svg": "assets/vendors/flag-icon-css/flags/1x1/sg.9eb47fe757c9.svg", "assets/vendors/flag-icon-css/flags/1x1/ro.svg": "assets/vendors/flag-icon-css/flags/1x1/ro.22278e1314d8.svg", "assets/vendors/flag-icon-css/flags/1x1/pw.svg": "assets/vendors/flag-icon-css/flags/1x1/pw.78aaead281d5.svg", "assets/vendors/flag-icon-css/flags/1x1/af.svg": "assets/vendors/flag-icon-css/flags/1x1/af.fa735e43100e.svg", "assets/vendors/flag-icon-css/flags/1x1/va.svg": "assets/vendors/flag-icon-css/flags/1x1/va.90e9f73abaa2.svg", "assets/vendors/flag-icon-css/flags/1x1/uy.svg": "assets/vendors/flag-icon-css/flags/1x1/uy.adbc4992aa0c.svg", "assets/vendors/flag-icon-css/flags/1x1/cx.svg": "assets/vendors/flag-icon-css/flags/1x1/cx.172a41ec42fd.svg", "assets/vendors/flag-icon-css/flags/1x1/lc.svg": "assets/vendors/flag-icon-css/flags/1x1/lc.c056c2a721c5.svg", "assets/vendors/flag-icon-css/flags/1x1/fj.svg": "assets/vendors/flag-icon-css/flags/1x1/fj.76a7a39e11d3.svg", "assets/vendors/flag-icon-css/flags/1x1/ad.svg": "assets/vendors/flag-icon-css/flags/1x1/ad.e15ddeabbfce.svg", "assets/vendors/flag-icon-css/flags/1x1/xk.svg": "assets/vendors/flag-icon-css/flags/1x1/xk.bd62029ec779.svg", "assets/vendors/flag-icon-css/flags/1x1/tt.svg": "assets/vendors/flag-icon-css/flags/1x1/tt.4705d420d21a.svg", "assets/vendors/flag-icon-css/flags/1x1/jp.svg": "assets/vendors/flag-icon-css/flags/1x1/jp.16a568ca9eb1.svg", "assets/vendors/flag-icon-css/flags/1x1/pe.svg": "assets/vendors/flag-icon-css/flags/1x1/pe.23591f9d72b1.svg", "assets/vendors/flag-icon-css/flags/1x1/cw.svg": "assets/vendors/flag-icon-css/flags/1x1/cw.69f19c22070d.svg", "assets/vendors/flag-icon-css/flags/1x1/er.svg": "assets/vendors/flag-icon-css/flags/1x1/er.bdfbf04ca256.svg", "assets/vendors/flag-icon-css/flags/1x1/om.svg": "assets/vendors/flag-icon-css/flags/1x1/om.b9b7d0bc1d35.svg", "assets/vendors/flag-icon-css/flags/1x1/sr.svg": "assets/vendors/flag-icon-css/flags/1x1/sr.be27d1ae7006.svg", "assets/vendors/flag-icon-css/flags/1x1/pt.svg": "assets/vendors/flag-icon-css/flags/1x1/pt.04fa443dfc5d.svg", "assets/vendors/flag-icon-css/flags/1x1/by.svg": "assets/vendors/flag-icon-css/flags/1x1/by.80b2d2dd1500.svg", "assets/vendors/flag-icon-css/flags/1x1/wf.svg": "assets/vendors/flag-icon-css/flags/1x1/wf.05522b9f1923.svg", "assets/vendors/flag-icon-css/flags/1x1/vu.svg": "assets/vendors/flag-icon-css/flags/1x1/vu.730801abb424.svg", "assets/vendors/flag-icon-css/flags/1x1/ly.svg": "assets/vendors/flag-icon-css/flags/1x1/ly.050ff9b00cb2.svg", "assets/vendors/flag-icon-css/flags/1x1/ec.svg": "assets/vendors/flag-icon-css/flags/1x1/ec.5e9624dfa7ec.svg", "assets/vendors/flag-icon-css/flags/1x1/ag.svg": "assets/vendors/flag-icon-css/flags/1x1/ag.53a600867bab.svg", "assets/vendors/flag-icon-css/flags/1x1/pr.svg": "assets/vendors/flag-icon-css/flags/1x1/pr.1d278b022fba.svg", "assets/vendors/flag-icon-css/flags/1x1/tr.svg": "assets/vendors/flag-icon-css/flags/1x1/tr.ce2e2e8e0650.svg", "assets/vendors/flag-icon-css/flags/1x1/eh.svg": "assets/vendors/flag-icon-css/flags/1x1/eh.2a0e164e96de.svg", "assets/vendors/flag-icon-css/flags/1x1/mm.svg": "assets/vendors/flag-icon-css/flags/1x1/mm.8d6d26bc590a.svg", "assets/vendors/flag-icon-css/flags/1x1/gn.svg": "assets/vendors/flag-icon-css/flags/1x1/gn.1ce64523708a.svg", "assets/vendors/flag-icon-css/flags/1x1/gb-eng.svg": "assets/vendors/flag-icon-css/flags/1x1/gb-eng.eabfeadc28e7.svg", "assets/vendors/flag-icon-css/flags/1x1/bh.svg": "assets/vendors/flag-icon-css/flags/1x1/bh.90ad3cbd95a2.svg", "assets/vendors/flag-icon-css/flags/1x1/pl.svg": "assets/vendors/flag-icon-css/flags/1x1/pl.3fe3bd51a504.svg", "assets/vendors/flag-icon-css/flags/1x1/us.svg": "assets/vendors/flag-icon-css/flags/1x1/us.8ec583188aba.svg", "assets/vendors/flag-icon-css/flags/1x1/sx.svg": "assets/vendors/flag-icon-css/flags/1x1/sx.a724800161ac.svg", "assets/vendors/flag-icon-css/flags/1x1/km.svg": "assets/vendors/flag-icon-css/flags/1x1/km.eb69abb63245.svg", "assets/vendors/flag-icon-css/flags/1x1/mc.svg": "assets/vendors/flag-icon-css/flags/1x1/mc.78528abed80a.svg", "assets/vendors/flag-icon-css/flags/1x1/lr.svg": "assets/vendors/flag-icon-css/flags/1x1/lr.6656f943933f.svg", "assets/vendors/flag-icon-css/flags/1x1/gf.svg": "assets/vendors/flag-icon-css/flags/1x1/gf.cabf9781aaaa.svg", "assets/vendors/flag-icon-css/flags/1x1/ck.svg": "assets/vendors/flag-icon-css/flags/1x1/ck.22bf8119f315.svg", "assets/vendors/flag-icon-css/flags/1x1/ru.svg": "assets/vendors/flag-icon-css/flags/1x1/ru.e3ee3b099783.svg", "assets/vendors/flag-icon-css/flags/1x1/sh.svg": "assets/vendors/flag-icon-css/flags/1x1/sh.487ef1c8b75a.svg", "assets/vendors/flag-icon-css/flags/1x1/cz.svg": "assets/vendors/flag-icon-css/flags/1x1/cz.490443104ecb.svg", "assets/vendors/flag-icon-css/flags/1x1/np.svg": "assets/vendors/flag-icon-css/flags/1x1/np.27f0f4e72e35.svg", "assets/vendors/flag-icon-css/flags/1x1/au.svg": "assets/vendors/flag-icon-css/flags/1x1/au.9b18ee0449e1.svg", "assets/vendors/flag-icon-css/flags/1x1/gg.svg": "assets/vendors/flag-icon-css/flags/1x1/gg.357e1e33666f.svg", "assets/vendors/flag-icon-css/flags/1x1/cr.svg": "assets/vendors/flag-icon-css/flags/1x1/cr.657d7dbcfdeb.svg", "assets/vendors/flag-icon-css/flags/1x1/ua.svg": "assets/vendors/flag-icon-css/flags/1x1/ua.841d259d582b.svg", "assets/vendors/flag-icon-css/flags/1x1/mh.svg": "assets/vendors/flag-icon-css/flags/1x1/mh.8f1f91348e69.svg", "assets/vendors/flag-icon-css/flags/1x1/ai.svg": "assets/vendors/flag-icon-css/flags/1x1/ai.9fe4d6b75d40.svg", "assets/vendors/flag-icon-css/flags/1x1/mz.svg": "assets/vendors/flag-icon-css/flags/1x1/mz.e99caf39cbb1.svg", "assets/vendors/flag-icon-css/flags/1x1/bb.svg": "assets/vendors/flag-icon-css/flags/1x1/bb.45c62450e2d6.svg", "assets/vendors/flag-icon-css/flags/1x1/jm.svg": "assets/vendors/flag-icon-css/flags/1x1/jm.b7b13124a406.svg", "assets/vendors/flag-icon-css/flags/1x1/lv.svg": "assets/vendors/flag-icon-css/flags/1x1/lv.f3c1274d1664.svg", "assets/vendors/flag-icon-css/flags/1x1/fk.svg": "assets/vendors/flag-icon-css/flags/1x1/fk.aeb2d58832c6.svg", "assets/vendors/flag-icon-css/flags/1x1/dj.svg": "assets/vendors/flag-icon-css/flags/1x1/dj.0c386d224ea2.svg", "assets/vendors/flag-icon-css/flags/1x1/um.svg": "assets/vendors/flag-icon-css/flags/1x1/um.3d347682d5c5.svg", "assets/vendors/flag-icon-css/flags/1x1/kg.svg": "assets/vendors/flag-icon-css/flags/1x1/kg.5908392a2d10.svg", "assets/vendors/flag-icon-css/flags/1x1/mp.svg": "assets/vendors/flag-icon-css/flags/1x1/mp.8a731cbc2f69.svg", "assets/vendors/flag-icon-css/flags/1x1/ky.svg": "assets/vendors/flag-icon-css/flags/1x1/ky.ef1f65378cda.svg", "assets/vendors/flag-icon-css/flags/1x1/ht.svg": "assets/vendors/flag-icon-css/flags/1x1/ht.34eb5f592af7.svg", "assets/vendors/flag-icon-css/flags/1x1/ss.svg": "assets/vendors/flag-icon-css/flags/1x1/ss.e3933b4455dc.svg", "assets/vendors/flag-icon-css/flags/1x1/mx.svg": "assets/vendors/flag-icon-css/flags/1x1/mx.3aa223c8cc48.svg", "assets/vendors/flag-icon-css/flags/1x1/it.svg": "assets/vendors/flag-icon-css/flags/1x1/it.22b99ae704f3.svg", "assets/vendors/flag-icon-css/flags/1x1/je.svg": "assets/vendors/flag-icon-css/flags/1x1/je.e170f442844c.svg", "assets/vendors/flag-icon-css/flags/1x1/qa.svg": "assets/vendors/flag-icon-css/flags/1x1/qa.78909a6f9bc3.svg", "assets/vendors/flag-icon-css/flags/1x1/do.svg": "assets/vendors/flag-icon-css/flags/1x1/do.07d2b1ed2aa9.svg", "assets/vendors/flag-icon-css/flags/1x1/mq.svg": "assets/vendors/flag-icon-css/flags/1x1/mq.a09e48650a20.svg", "assets/vendors/flag-icon-css/flags/1x1/ws.svg": "assets/vendors/flag-icon-css/flags/1x1/ws.3ea6d44f91f0.svg", "assets/vendors/flag-icon-css/flags/1x1/at.svg": "assets/vendors/flag-icon-css/flags/1x1/at.5ab33f744e92.svg", "assets/vendors/flag-icon-css/flags/1x1/il.svg": "assets/vendors/flag-icon-css/flags/1x1/il.c36a011de460.svg", "assets/vendors/flag-icon-css/flags/1x1/sz.svg": "assets/vendors/flag-icon-css/flags/1x1/sz.dc2faeb7bafa.svg", "assets/vendors/flag-icon-css/flags/1x1/tf.svg": "assets/vendors/flag-icon-css/flags/1x1/tf.2e7dc1af2d97.svg", "assets/vendors/flag-icon-css/flags/1x1/mv.svg": "assets/vendors/flag-icon-css/flags/1x1/mv.0fdc08c6985e.svg", "assets/vendors/flag-icon-css/flags/1x1/gb-wls.svg": "assets/vendors/flag-icon-css/flags/1x1/gb-wls.85f8b84246b2.svg", "assets/vendors/flag-icon-css/flags/1x1/lu.svg": "assets/vendors/flag-icon-css/flags/1x1/lu.2585715a069b.svg", "assets/vendors/flag-icon-css/flags/1x1/gr.svg": "assets/vendors/flag-icon-css/flags/1x1/gr.0bed56a8b601.svg", "assets/vendors/flag-icon-css/flags/1x1/ge.svg": "assets/vendors/flag-icon-css/flags/1x1/ge.d3665bf12d34.svg", "assets/vendors/flag-icon-css/flags/1x1/sa.svg": "assets/vendors/flag-icon-css/flags/1x1/sa.135d0c86322f.svg", "assets/vendors/flag-icon-css/flags/1x1/kp.svg": "assets/vendors/flag-icon-css/flags/1x1/kp.f08daf335790.svg", "assets/vendors/flag-icon-css/flags/1x1/zm.svg": "assets/vendors/flag-icon-css/flags/1x1/zm.3eef5dc07668.svg", "assets/vendors/flag-icon-css/flags/1x1/gm.svg": "assets/vendors/flag-icon-css/flags/1x1/gm.414139d5039a.svg", "assets/vendors/flag-icon-css/flags/1x1/bf.svg": "assets/vendors/flag-icon-css/flags/1x1/bf.48eb94de0b25.svg", "assets/vendors/flag-icon-css/flags/1x1/th.svg": "assets/vendors/flag-icon-css/flags/1x1/th.904dd7853b62.svg", "assets/vendors/flag-icon-css/flags/1x1/bo.svg": "assets/vendors/flag-icon-css/flags/1x1/bo.eab17936c2d9.svg", "assets/vendors/flag-icon-css/flags/1x1/cd.svg": "assets/vendors/flag-icon-css/flags/1x1/cd.b43f872e1441.svg", "assets/vendors/flag-icon-css/flags/1x1/et.svg": "assets/vendors/flag-icon-css/flags/1x1/et.1d986679c467.svg", "assets/vendors/flag-icon-css/flags/1x1/gs.svg": "assets/vendors/flag-icon-css/flags/1x1/gs.6adf96a85713.svg", "assets/vendors/flag-icon-css/flags/1x1/io.svg": "assets/vendors/flag-icon-css/flags/1x1/io.a45231d40c5e.svg", "assets/vendors/flag-icon-css/flags/1x1/ga.svg": "assets/vendors/flag-icon-css/flags/1x1/ga.33d27fe1d14e.svg", "assets/vendors/flag-icon-css/flags/1x1/bz.svg": "assets/vendors/flag-icon-css/flags/1x1/bz.e6b5e204d3da.svg", "assets/vendors/flag-icon-css/flags/1x1/tz.svg": "assets/vendors/flag-icon-css/flags/1x1/tz.d02545a1e6ca.svg", "assets/vendors/flag-icon-css/flags/1x1/es-ca.svg": "assets/vendors/flag-icon-css/flags/1x1/es-ca.a35e6a4a92e9.svg", "assets/vendors/flag-icon-css/flags/1x1/cu.svg": "assets/vendors/flag-icon-css/flags/1x1/cu.0b42edabb93e.svg", "assets/vendors/flag-icon-css/flags/1x1/fo.svg": "assets/vendors/flag-icon-css/flags/1x1/fo.329cbed56602.svg", "assets/vendors/flag-icon-css/flags/1x1/pn.svg": "assets/vendors/flag-icon-css/flags/1x1/pn.48bd62e408e5.svg", "assets/vendors/flag-icon-css/flags/1x1/hk.svg": "assets/vendors/flag-icon-css/flags/1x1/hk.4a0f09ba94fb.svg", "assets/vendors/flag-icon-css/flags/1x1/ca.svg": "assets/vendors/flag-icon-css/flags/1x1/ca.8678fc67f7eb.svg", "assets/vendors/flag-icon-css/flags/1x1/ms.svg": "assets/vendors/flag-icon-css/flags/1x1/ms.ad88044d48d7.svg", "assets/vendors/flag-icon-css/flags/1x1/iq.svg": "assets/vendors/flag-icon-css/flags/1x1/iq.8d936728f892.svg", "assets/vendors/flag-icon-css/flags/1x1/gw.svg": "assets/vendors/flag-icon-css/flags/1x1/gw.5ecbd93cc2ee.svg", "assets/vendors/flag-icon-css/flags/1x1/na.svg": "assets/vendors/flag-icon-css/flags/1x1/na.74257fb27e11.svg", "assets/vendors/flag-icon-css/flags/1x1/bd.svg": "assets/vendors/flag-icon-css/flags/1x1/bd.c4a1485f3606.svg", "assets/vendors/flag-icon-css/flags/1x1/gi.svg": "assets/vendors/flag-icon-css/flags/1x1/gi.b0015a50c9f5.svg", "assets/vendors/flag-icon-css/flags/1x1/ee.svg": "assets/vendors/flag-icon-css/flags/1x1/ee.9e932a62565e.svg", "assets/vendors/flag-icon-css/flags/1x1/re.svg": "assets/vendors/flag-icon-css/flags/1x1/re.01fea3b62ac2.svg", "assets/vendors/flag-icon-css/flags/1x1/ve.svg": "assets/vendors/flag-icon-css/flags/1x1/ve.9f23d9626b92.svg", "assets/vendors/flag-icon-css/flags/1x1/co.svg": "assets/vendors/flag-icon-css/flags/1x1/co.41244c207c1c.svg", "assets/vendors/flag-icon-css/flags/1x1/mr.svg": "assets/vendors/flag-icon-css/flags/1x1/mr.bf379763ac17.svg", "assets/vendors/flag-icon-css/flags/1x1/sl.svg": "assets/vendors/flag-icon-css/flags/1x1/sl.f6315f743d7d.svg", "assets/vendors/flag-icon-css/flags/1x1/kr.svg": "assets/vendors/flag-icon-css/flags/1x1/kr.7fb0181b38e9.svg", "assets/vendors/flag-icon-css/flags/1x1/za.svg": "assets/vendors/flag-icon-css/flags/1x1/za.67ff2e108ce3.svg", "assets/vendors/flag-icon-css/flags/1x1/la.svg": "assets/vendors/flag-icon-css/flags/1x1/la.6b86f25a0d2d.svg", "assets/vendors/flag-icon-css/flags/1x1/vi.svg": "assets/vendors/flag-icon-css/flags/1x1/vi.0aa782108fb3.svg", "assets/vendors/flag-icon-css/flags/1x1/de.svg": "assets/vendors/flag-icon-css/flags/1x1/de.4d7bac3b0b9a.svg", "assets/vendors/flag-icon-css/flags/1x1/gu.svg": "assets/vendors/flag-icon-css/flags/1x1/gu.64936a10d41e.svg", "assets/vendors/flag-icon-css/flags/1x1/nr.svg": "assets/vendors/flag-icon-css/flags/1x1/nr.2ef5b7c8f28f.svg", "assets/vendors/flag-icon-css/flags/1x1/am.svg": "assets/vendors/flag-icon-css/flags/1x1/am.c86a9e1691e7.svg", "assets/vendors/flag-icon-css/flags/1x1/hr.svg": "assets/vendors/flag-icon-css/flags/1x1/hr.88f38f33e9c5.svg", "assets/vendors/flag-icon-css/flags/1x1/ps.svg": "assets/vendors/flag-icon-css/flags/1x1/ps.2992f9b92974.svg", "assets/vendors/flag-icon-css/flags/1x1/nf.svg": "assets/vendors/flag-icon-css/flags/1x1/nf.801ee09f9641.svg", "assets/vendors/flag-icon-css/flags/1x1/lb.svg": "assets/vendors/flag-icon-css/flags/1x1/lb.56f32195732a.svg", "assets/vendors/flag-icon-css/flags/1x1/gl.svg": "assets/vendors/flag-icon-css/flags/1x1/gl.48bf3e4e3fda.svg", "assets/vendors/flag-icon-css/flags/1x1/cm.svg": "assets/vendors/flag-icon-css/flags/1x1/cm.c972441e6e45.svg", "assets/vendors/flag-icon-css/flags/1x1/ae.svg": "assets/vendors/flag-icon-css/flags/1x1/ae.7847726d0663.svg", "assets/vendors/flag-icon-css/flags/1x1/ci.svg": "assets/vendors/flag-icon-css/flags/1x1/ci.26a62321690c.svg", "assets/vendors/flag-icon-css/flags/1x1/mg.svg": "assets/vendors/flag-icon-css/flags/1x1/mg.91e10ba084cc.svg", "assets/vendors/flag-icon-css/flags/1x1/tw.svg": "assets/vendors/flag-icon-css/flags/1x1/tw.26cc9d596b2d.svg", "assets/vendors/flag-icon-css/flags/1x1/br.svg": "assets/vendors/flag-icon-css/flags/1x1/br.ef701aba4f5d.svg", "assets/vendors/flag-icon-css/flags/1x1/dm.svg": "assets/vendors/flag-icon-css/flags/1x1/dm.664bf04224fd.svg", "assets/vendors/flag-icon-css/flags/1x1/pk.svg": "assets/vendors/flag-icon-css/flags/1x1/pk.b67f80e0c74a.svg", "assets/vendors/flag-icon-css/flags/1x1/bm.svg": "assets/vendors/flag-icon-css/flags/1x1/bm.09839e2cd707.svg", "assets/vendors/flag-icon-css/flags/1x1/bj.svg": "assets/vendors/flag-icon-css/flags/1x1/bj.b6387659d755.svg", "assets/vendors/flag-icon-css/flags/1x1/ki.svg": "assets/vendors/flag-icon-css/flags/1x1/ki.cdeef8df88cf.svg", "assets/vendors/flag-icon-css/flags/1x1/yt.svg": "assets/vendors/flag-icon-css/flags/1x1/yt.b6042b9cfb43.svg", "assets/vendors/flag-icon-css/flags/1x1/fm.svg": "assets/vendors/flag-icon-css/flags/1x1/fm.3f19d612c1d9.svg", "assets/vendors/flag-icon-css/flags/1x1/dz.svg": "assets/vendors/flag-icon-css/flags/1x1/dz.b03e5aec7ad5.svg", "assets/vendors/flag-icon-css/flags/1x1/ni.svg": "assets/vendors/flag-icon-css/flags/1x1/ni.baafd7d7fc1b.svg", "assets/vendors/flag-icon-css/flags/1x1/pa.svg": "assets/vendors/flag-icon-css/flags/1x1/pa.beb40ab6cce7.svg", "assets/vendors/flag-icon-css/flags/1x1/mu.svg": "assets/vendors/flag-icon-css/flags/1x1/mu.67c8f3621446.svg", "assets/vendors/flag-icon-css/flags/1x1/gt.svg": "assets/vendors/flag-icon-css/flags/1x1/gt.d6b5b664755a.svg", "assets/vendors/flag-icon-css/flags/1x1/vg.svg": "assets/vendors/flag-icon-css/flags/1x1/vg.a796b16d8f1c.svg", "assets/vendors/flag-icon-css/flags/1x1/kw.svg": "assets/vendors/flag-icon-css/flags/1x1/kw.33b3292eb308.svg", "assets/vendors/flag-icon-css/flags/1x1/gq.svg": "assets/vendors/flag-icon-css/flags/1x1/gq.80b56bda2200.svg", "assets/vendors/flag-icon-css/flags/1x1/tj.svg": "assets/vendors/flag-icon-css/flags/1x1/tj.980d12c94105.svg", "assets/vendors/flag-icon-css/flags/1x1/ir.svg": "assets/vendors/flag-icon-css/flags/1x1/ir.7bf140ab46a7.svg", "assets/vendors/flag-icon-css/flags/1x1/kh.svg": "assets/vendors/flag-icon-css/flags/1x1/kh.61a4b374334e.svg", "assets/vendors/flag-icon-css/flags/1x1/to.svg": "assets/vendors/flag-icon-css/flags/1x1/to.238ef1cd63bf.svg", "assets/vendors/flag-icon-css/flags/1x1/eg.svg": "assets/vendors/flag-icon-css/flags/1x1/eg.2ea321dd4b0a.svg", "assets/vendors/flag-icon-css/flags/1x1/be.svg": "assets/vendors/flag-icon-css/flags/1x1/be.f1e78c8b3266.svg", "assets/vendors/flag-icon-css/flags/1x1/tg.svg": "assets/vendors/flag-icon-css/flags/1x1/tg.29fa137c095a.svg", "assets/vendors/flag-icon-css/flags/1x1/so.svg": "assets/vendors/flag-icon-css/flags/1x1/so.c1561217671d.svg", "assets/vendors/flag-icon-css/flags/1x1/mt.svg": "assets/vendors/flag-icon-css/flags/1x1/mt.f6e3733c70db.svg", "assets/vendors/flag-icon-css/flags/1x1/bs.svg": "assets/vendors/flag-icon-css/flags/1x1/bs.6fe877e157af.svg", "assets/vendors/flag-icon-css/flags/1x1/pm.svg": "assets/vendors/flag-icon-css/flags/1x1/pm.89993b1ff27b.svg", "assets/vendors/flag-icon-css/flags/1x1/nu.svg": "assets/vendors/flag-icon-css/flags/1x1/nu.1db5a99d1f54.svg", "assets/vendors/flag-icon-css/flags/1x1/hn.svg": "assets/vendors/flag-icon-css/flags/1x1/hn.c94622ad395a.svg", "assets/vendors/flag-icon-css/flags/1x1/ne.svg": "assets/vendors/flag-icon-css/flags/1x1/ne.e56edd30b77a.svg", "assets/vendors/flag-icon-css/flags/1x1/pf.svg": "assets/vendors/flag-icon-css/flags/1x1/pf.2a69c5818540.svg", "assets/vendors/flag-icon-css/flags/1x1/bn.svg": "assets/vendors/flag-icon-css/flags/1x1/bn.0adbb6646a1e.svg", "assets/vendors/flag-icon-css/flags/1x1/sj.svg": "assets/vendors/flag-icon-css/flags/1x1/sj.ecbc9e939c38.svg", "assets/vendors/flag-icon-css/flags/1x1/sk.svg": "assets/vendors/flag-icon-css/flags/1x1/sk.a5af0a28a32c.svg", "assets/vendors/flag-icon-css/flags/1x1/st.svg": "assets/vendors/flag-icon-css/flags/1x1/st.d0a56dbbee36.svg", "assets/vendors/flag-icon-css/flags/1x1/ml.svg": "assets/vendors/flag-icon-css/flags/1x1/ml.204b0da4b499.svg", "assets/vendors/flag-icon-css/flags/1x1/hm.svg": "assets/vendors/flag-icon-css/flags/1x1/hm.fc838ac0bb4f.svg", "assets/vendors/flag-icon-css/flags/1x1/vc.svg": "assets/vendors/flag-icon-css/flags/1x1/vc.bbb52fa07562.svg", "assets/vendors/flag-icon-css/flags/1x1/mf.svg": "assets/vendors/flag-icon-css/flags/1x1/mf.487f7bd7fd30.svg", "assets/vendors/flag-icon-css/flags/1x1/cg.svg": "assets/vendors/flag-icon-css/flags/1x1/cg.8373836c83f0.svg", "assets/vendors/flag-icon-css/flags/1x1/cf.svg": "assets/vendors/flag-icon-css/flags/1x1/cf.1bc217dc2a40.svg", "assets/vendors/flag-icon-css/flags/1x1/hu.svg": "assets/vendors/flag-icon-css/flags/1x1/hu.e5e334fdd028.svg", "assets/vendors/flag-icon-css/flags/1x1/ch.svg": "assets/vendors/flag-icon-css/flags/1x1/ch.252c409ba2d2.svg", "assets/vendors/flag-icon-css/flags/1x1/mk.svg": "assets/vendors/flag-icon-css/flags/1x1/mk.2413b10706c9.svg", "assets/vendors/flag-icon-css/flags/1x1/mo.svg": "assets/vendors/flag-icon-css/flags/1x1/mo.de26729cbe5d.svg", "assets/vendors/flag-icon-css/flags/1x1/me.svg": "assets/vendors/flag-icon-css/flags/1x1/me.2d0c8f786f51.svg", "assets/vendors/flag-icon-css/flags/1x1/ug.svg": "assets/vendors/flag-icon-css/flags/1x1/ug.6d6f88960e15.svg", "assets/vendors/flag-icon-css/flags/1x1/cy.svg": "assets/vendors/flag-icon-css/flags/1x1/cy.9f04989a2340.svg", "assets/vendors/flag-icon-css/flags/1x1/tn.svg": "assets/vendors/flag-icon-css/flags/1x1/tn.fea87146ed08.svg", "assets/vendors/flag-icon-css/flags/1x1/is.svg": "assets/vendors/flag-icon-css/flags/1x1/is.ae44c07e894b.svg", "assets/vendors/flag-icon-css/flags/1x1/gh.svg": "assets/vendors/flag-icon-css/flags/1x1/gh.77872d15b6a6.svg", "assets/vendors/flag-icon-css/flags/1x1/se.svg": "assets/vendors/flag-icon-css/flags/1x1/se.b039bdb8e50c.svg", "assets/vendors/flag-icon-css/flags/1x1/gb-nir.svg": "assets/vendors/flag-icon-css/flags/1x1/gb-nir.9cad35c46f77.svg", "assets/vendors/flag-icon-css/flags/1x1/aq.svg": "assets/vendors/flag-icon-css/flags/1x1/aq.65448909a823.svg", "assets/vendors/flag-icon-css/flags/1x1/nl.svg": "assets/vendors/flag-icon-css/flags/1x1/nl.390aa40fd896.svg", "assets/vendors/flag-icon-css/flags/1x1/ao.svg": "assets/vendors/flag-icon-css/flags/1x1/ao.ab8cc21b5392.svg", "assets/vendors/flag-icon-css/flags/1x1/im.svg": "assets/vendors/flag-icon-css/flags/1x1/im.ac0c825e7685.svg", "assets/vendors/flag-icon-css/flags/1x1/ke.svg": "assets/vendors/flag-icon-css/flags/1x1/ke.87900162ad67.svg", "assets/vendors/flag-icon-css/flags/1x1/bq.svg": "assets/vendors/flag-icon-css/flags/1x1/bq.d6da2e848d83.svg", "assets/vendors/flag-icon-css/flags/1x1/si.svg": "assets/vendors/flag-icon-css/flags/1x1/si.63ba8c45578b.svg", "assets/vendors/flag-icon-css/flags/1x1/gb.svg": "assets/vendors/flag-icon-css/flags/1x1/gb.5db9fea0ec9e.svg", "assets/vendors/flag-icon-css/flags/1x1/ar.svg": "assets/vendors/flag-icon-css/flags/1x1/ar.78827b0be4fd.svg", "assets/vendors/flag-icon-css/flags/1x1/lt.svg": "assets/vendors/flag-icon-css/flags/1x1/lt.70975be09055.svg", "assets/vendors/flag-icon-css/flags/1x1/lk.svg": "assets/vendors/flag-icon-css/flags/1x1/lk.f54e1ef96c3b.svg", "assets/vendors/flag-icon-css/flags/1x1/pg.svg": "assets/vendors/flag-icon-css/flags/1x1/pg.0b07d4189444.svg", "assets/vendors/flag-icon-css/flags/1x1/aw.svg": "assets/vendors/flag-icon-css/flags/1x1/aw.f159ec168ea0.svg", "assets/vendors/flag-icon-css/flags/1x1/tk.svg": "assets/vendors/flag-icon-css/flags/1x1/tk.7aaccddb93a5.svg", "assets/vendors/flag-icon-css/flags/1x1/dk.svg": "assets/vendors/flag-icon-css/flags/1x1/dk.d046fb5b6363.svg", "assets/vendors/flag-icon-css/flags/1x1/cl.svg": "assets/vendors/flag-icon-css/flags/1x1/cl.6d63ff70245f.svg", "assets/vendors/flag-icon-css/flags/1x1/gy.svg": "assets/vendors/flag-icon-css/flags/1x1/gy.0653b318bc72.svg", "assets/vendors/flag-icon-css/flags/1x1/sy.svg": "assets/vendors/flag-icon-css/flags/1x1/sy.73690f50d6d4.svg", "assets/vendors/flag-icon-css/flags/1x1/bg.svg": "assets/vendors/flag-icon-css/flags/1x1/bg.7163fe7683bf.svg", "assets/vendors/flag-icon-css/flags/1x1/vn.svg": "assets/vendors/flag-icon-css/flags/1x1/vn.a00814821923.svg", "assets/vendors/flag-icon-css/flags/1x1/mw.svg": "assets/vendors/flag-icon-css/flags/1x1/mw.baf490bf505c.svg", "assets/vendors/flag-icon-css/flags/1x1/eu.svg": "assets/vendors/flag-icon-css/flags/1x1/eu.4c73f57cb89b.svg", "assets/vendors/flag-icon-css/flags/1x1/bi.svg": "assets/vendors/flag-icon-css/flags/1x1/bi.75d5af3debe2.svg", "assets/vendors/flag-icon-css/flags/1x1/my.svg": "assets/vendors/flag-icon-css/flags/1x1/my.263aea34bcf7.svg", "assets/vendors/flag-icon-css/flags/1x1/kz.svg": "assets/vendors/flag-icon-css/flags/1x1/kz.a19240f60581.svg", "assets/vendors/flag-icon-css/flags/1x1/bw.svg": "assets/vendors/flag-icon-css/flags/1x1/bw.d9e5e45f7cab.svg", "assets/vendors/flag-icon-css/flags/1x1/bt.svg": "assets/vendors/flag-icon-css/flags/1x1/bt.dbb1623f2a2b.svg", "assets/vendors/flag-icon-css/flags/1x1/mn.svg": "assets/vendors/flag-icon-css/flags/1x1/mn.933606d51156.svg", "assets/vendors/flag-icon-css/flags/1x1/uz.svg": "assets/vendors/flag-icon-css/flags/1x1/uz.ca892343cb96.svg", "assets/vendors/flag-icon-css/flags/1x1/nz.svg": "assets/vendors/flag-icon-css/flags/1x1/nz.7dab6e5e9d9e.svg", "assets/vendors/flag-icon-css/flags/1x1/az.svg": "assets/vendors/flag-icon-css/flags/1x1/az.0b4258df0249.svg", "assets/vendors/flag-icon-css/flags/1x1/jo.svg": "assets/vendors/flag-icon-css/flags/1x1/jo.5130279865a7.svg", "assets/vendors/flag-icon-css/flags/1x1/ba.svg": "assets/vendors/flag-icon-css/flags/1x1/ba.a9dbadd71245.svg", "assets/vendors/flag-icon-css/flags/1x1/md.svg": "assets/vendors/flag-icon-css/flags/1x1/md.75ec533ab81d.svg", "assets/vendors/flag-icon-css/flags/1x1/ls.svg": "assets/vendors/flag-icon-css/flags/1x1/ls.533cb320083a.svg", "assets/vendors/flag-icon-css/flags/1x1/tv.svg": "assets/vendors/flag-icon-css/flags/1x1/tv.a595f49d6d55.svg", "assets/vendors/flag-icon-css/flags/1x1/al.svg": "assets/vendors/flag-icon-css/flags/1x1/al.46612c2737dd.svg", "assets/vendors/flag-icon-css/flags/1x1/bv.svg": "assets/vendors/flag-icon-css/flags/1x1/bv.b70ab2f2a1fd.svg", "assets/vendors/flag-icon-css/flags/1x1/es.svg": "assets/vendors/flag-icon-css/flags/1x1/es.afff247381e7.svg", "assets/vendors/flag-icon-css/flags/1x1/ax.svg": "assets/vendors/flag-icon-css/flags/1x1/ax.fdd00c438df1.svg", "assets/vendors/flag-icon-css/flags/1x1/as.svg": "assets/vendors/flag-icon-css/flags/1x1/as.27f3e372f5d3.svg", "assets/vendors/flag-icon-css/flags/1x1/tl.svg": "assets/vendors/flag-icon-css/flags/1x1/tl.0616faaafebb.svg", "assets/vendors/flag-icon-css/flags/1x1/sd.svg": "assets/vendors/flag-icon-css/flags/1x1/sd.7ab061d859c1.svg", "assets/vendors/flag-icon-css/flags/1x1/li.svg": "assets/vendors/flag-icon-css/flags/1x1/li.748d1f9967c0.svg", "assets/vendors/flag-icon-css/flags/1x1/nc.svg": "assets/vendors/flag-icon-css/flags/1x1/nc.d393b8faea4e.svg", "assets/vendors/flag-icon-css/flags/1x1/gd.svg": "assets/vendors/flag-icon-css/flags/1x1/gd.56fdbab2ad5e.svg", "assets/vendors/flag-icon-css/flags/1x1/zw.svg": "assets/vendors/flag-icon-css/flags/1x1/zw.8b8854659c43.svg", "assets/vendors/flag-icon-css/flags/1x1/ma.svg": "assets/vendors/flag-icon-css/flags/1x1/ma.bee9c05416fd.svg", "assets/vendors/flag-icon-css/flags/1x1/tm.svg": "assets/vendors/flag-icon-css/flags/1x1/tm.ea365f332bb0.svg", "assets/vendors/flag-icon-css/flags/1x1/fr.svg": "assets/vendors/flag-icon-css/flags/1x1/fr.f8952213641b.svg", "assets/vendors/flag-icon-css/flags/1x1/rw.svg": "assets/vendors/flag-icon-css/flags/1x1/rw.997fe41bfffc.svg", "assets/vendors/flag-icon-css/flags/1x1/ie.svg": "assets/vendors/flag-icon-css/flags/1x1/ie.798a56e04350.svg", "assets/vendors/flag-icon-css/flags/1x1/no.svg": "assets/vendors/flag-icon-css/flags/1x1/no.b7a21f544f61.svg", "assets/vendors/flag-icon-css/flags/1x1/id.svg": "assets/vendors/flag-icon-css/flags/1x1/id.9f708fe5bf60.svg", "assets/vendors/flag-icon-css/flags/1x1/cv.svg": "assets/vendors/flag-icon-css/flags/1x1/cv.20a8cfffe0e9.svg", "assets/vendors/flag-icon-css/flags/1x1/fi.svg": "assets/vendors/flag-icon-css/flags/1x1/fi.b48413bec577.svg", "assets/vendors/flag-icon-css/flags/1x1/gp.svg": "assets/vendors/flag-icon-css/flags/1x1/gp.c2c4da0e6afb.svg", "assets/vendors/flag-icon-css/flags/1x1/sm.svg": "assets/vendors/flag-icon-css/flags/1x1/sm.f56650007eb0.svg", "assets/vendors/flag-icon-css/flags/1x1/cc.svg": "assets/vendors/flag-icon-css/flags/1x1/cc.12b2a48420c7.svg", "assets/vendors/flag-icon-css/flags/1x1/ng.svg": "assets/vendors/flag-icon-css/flags/1x1/ng.520463e155c2.svg", "assets/vendors/flag-icon-css/flags/1x1/in.svg": "assets/vendors/flag-icon-css/flags/1x1/in.209ae8e95857.svg", "assets/vendors/flag-icon-css/flags/1x1/sn.svg": "assets/vendors/flag-icon-css/flags/1x1/sn.d2bec7efb024.svg", "assets/vendors/flag-icon-css/flags/1x1/kn.svg": "assets/vendors/flag-icon-css/flags/1x1/kn.4ad12564dce8.svg", "assets/vendors/flag-icon-css/flags/1x1/ye.svg": "assets/vendors/flag-icon-css/flags/1x1/ye.d13e1629bdb0.svg", "assets/vendors/flag-icon-css/flags/1x1/sv.svg": "assets/vendors/flag-icon-css/flags/1x1/sv.26ee88728251.svg", "assets/vendors/flag-icon-css/flags/1x1/py.svg": "assets/vendors/flag-icon-css/flags/1x1/py.a70b32d0609b.svg", "assets/vendors/flag-icon-css/flags/1x1/ph.svg": "assets/vendors/flag-icon-css/flags/1x1/ph.6ae85442fa90.svg", "assets/vendors/flag-icon-css/flags/1x1/tc.svg": "assets/vendors/flag-icon-css/flags/1x1/tc.47c8276114b1.svg", "assets/vendors/flag-icon-css/flags/1x1/sb.svg": "assets/vendors/flag-icon-css/flags/1x1/sb.d64e984857cd.svg", "assets/vendors/flag-icon-css/flags/1x1/gb-sct.svg": "assets/vendors/flag-icon-css/flags/1x1/gb-sct.31ef8bcf9416.svg", "assets/vendors/flag-icon-css/flags/1x1/un.svg": "assets/vendors/flag-icon-css/flags/1x1/un.e6aabbd55ef6.svg", "assets/vendors/flag-icon-css/flags/1x1/bl.svg": "assets/vendors/flag-icon-css/flags/1x1/bl.4d724b8ec2c5.svg", "assets/vendors/flag-icon-css/flags/1x1/cn.svg": "assets/vendors/flag-icon-css/flags/1x1/cn.a94c93941a4d.svg", "assets/vendors/flag-icon-css/flags/1x1/rs.svg": "assets/vendors/flag-icon-css/flags/1x1/rs.d00d37d24860.svg", "assets/vendors/flag-icon-css/flags/1x1/td.svg": "assets/vendors/flag-icon-css/flags/1x1/td.f37a395c81f2.svg", "admin/js/vendor/select2/select2.full.min.js": "admin/js/vendor/select2/select2.full.min.fcd7500d8e13.js", "admin/js/vendor/select2/select2.full.js": "admin/js/vendor/select2/select2.full.c2afdeda3058.js", "admin/js/vendor/select2/LICENSE.md": "admin/js/vendor/select2/LICENSE.f94142512c91.md", "admin/js/vendor/jquery/jquery.min.js": "admin/js/vendor/jquery/jquery.min.dc5e7f18c8d3.js", "admin/js/vendor/jquery/jquery.js": "admin/js/vendor/jquery/jquery.23c7c5d2d131.js", "admin/js/vendor/jquery/LICENSE.txt": "admin/js/vendor/jquery/LICENSE.75308107741f.txt", "admin/js/vendor/xregexp/xregexp.js": "admin/js/vendor/xregexp/xregexp.efda034b9537.js", "admin/js/vendor/xregexp/xregexp.min.js": "admin/js/vendor/xregexp/xregexp.min.b0439563a5d3.js", "admin/js/vendor/xregexp/LICENSE.txt": "admin/js/vendor/xregexp/LICENSE.bf79e414957a.txt", "admin/css/vendor/select2/select2.min.css": "admin/css/vendor/select2/select2.min.9f54e6414f87.css", "admin/css/vendor/select2/LICENSE-SELECT2.md": "admin/css/vendor/select2/LICENSE-SELECT2.f94142512c91.md", "admin/css/vendor/select2/select2.css": "admin/css/vendor/select2/select2.a2194c262648.css", "assets/vendors/mdi/css/materialdesignicons.min.css.map": "assets/vendors/mdi/css/materialdesignicons.min.css.4cd50bf9558f.map", "assets/vendors/mdi/css/materialdesignicons.min.css": "assets/vendors/mdi/css/materialdesignicons.min.2ed2a2e2e03f.css", "assets/vendors/mdi/fonts/materialdesignicons-webfont.eot": "assets/vendors/mdi/fonts/materialdesignicons-webfont.541e65fb46e4.eot", "assets/vendors/mdi/fonts/materialdesignicons-webfont.woff": "assets/vendors/mdi/fonts/materialdesignicons-webfont.ff13d121c1a1.woff", "assets/vendors/mdi/fonts/materialdesignicons-webfont.woff2": "assets/vendors/mdi/fonts/materialdesignicons-webfont.c61b9c12f68e.woff2", "assets/vendors/mdi/fonts/materialdesignicons-webfont.ttf": "assets/vendors/mdi/fonts/materialdesignicons-webfont.fc03f7f15fac.ttf", "assets/vendors/flag-icon-css/css/flag-icon.min.css": "assets/vendors/flag-icon-css/css/flag-icon.min.9822bb510cdf.css", "assetz/vendor/glightbox/js/glightbox.min.js": "assetz/vendor/glightbox/js/glightbox.min.3a40d59d5244.js", "assetz/vendor/glightbox/js/glightbox.js": "assetz/vendor/glightbox/js/glightbox.1638ff0a89b7.js", "assetz/vendor/glightbox/css/glightbox.css": "assetz/vendor/glightbox/css/glightbox.7e2604695f55.css", "assetz/vendor/glightbox/css/glightbox.min.css": "assetz/vendor/glightbox/css/glightbox.min.f69035b3cab2.css", "assetz/vendor/bootstrap/js/bootstrap.bundle.js.map": "assetz/vendor/bootstrap/js/bootstrap.bundle.js.8798737ad8c7.map", "assetz/vendor/bootstrap/js/bootstrap.esm.min.js": "assetz/vendor/bootstrap/js/bootstrap.esm.min.9bce7dc2435a.js", "assetz/vendor/bootstrap/js/bootstrap.min.js": "assetz/vendor/bootstrap/js/bootstrap.min.b5730588db13.js", "assetz/vendor/bootstrap/js/bootstrap.js": "assetz/vendor/bootstrap/js/bootstrap.79b0236a5c46.js", "assetz/vendor/bootstrap/js/bootstrap.min.js.map": "assetz/vendor/bootstrap/js/bootstrap.min.js.b3d5e224e7d0.map", "assetz/vendor/bootstrap/js/bootstrap.bundle.js": "assetz/vendor/bootstrap/js/bootstrap.bundle.5897b2158dd1.js", "assetz/vendor/bootstrap/js/bootstrap.js.map": "assetz/vendor/bootstrap/js/bootstrap.js.98e3e9170c55.map", "assetz/vendor/bootstrap/js/bootstrap.bundle.min.js.map": "assetz/vendor/bootstrap/js/bootstrap.bundle.min.js.c904be4184f5.map", "assetz/vendor/bootstrap/js/bootstrap.esm.min.js.map": "assetz/vendor/bootstrap/js/bootstrap.esm.min.js.0b17d72567e5.map", "assetz/vendor/bootstrap/js/bootstrap.esm.js.map": "assetz/vendor/bootstrap/js/bootstrap.esm.js.32001e141fbe.map", "assetz/vendor/bootstrap/js/bootstrap.bundle.min.js": "assetz/vendor/bootstrap/js/bootstrap.bundle.min.8831aa095cde.js", "assetz/vendor/bootstrap/js/bootstrap.esm.js": "assetz/vendor/bootstrap/js/bootstrap.esm.356b5745959f.js", "assetz/vendor/bootstrap/css/bootstrap-reboot.rtl.min.css": "assetz/vendor/bootstrap/css/bootstrap-reboot.rtl.min.48d2515c394e.css", "assetz/vendor/bootstrap/css/bootstrap.min.css.map": "assetz/vendor/bootstrap/css/bootstrap.min.css.c48fe844f1ac.map", "assetz/vendor/bootstrap/css/bootstrap-reboot.css.map": "assetz/vendor/bootstrap/css/bootstrap-reboot.css.cb963247ca59.map", "assetz/vendor/bootstrap/css/bootstrap-grid.css.map": "assetz/vendor/bootstrap/css/bootstrap-grid.css.a4eb69f381bc.map", "assetz/vendor/bootstrap/css/bootstrap.css.map": "assetz/vendor/bootstrap/css/bootstrap.css.1e1403b4db1d.map", "assetz/vendor/bootstrap/css/bootstrap-reboot.rtl.min.css.map": "assetz/vendor/bootstrap/css/bootstrap-reboot.rtl.min.css.d86e44129126.map", "assetz/vendor/bootstrap/css/bootstrap-reboot.min.css": "assetz/vendor/bootstrap/css/bootstrap-reboot.min.0c7f9cfae220.css", "assetz/vendor/bootstrap/css/bootstrap-grid.rtl.min.css.map": "assetz/vendor/bootstrap/css/bootstrap-grid.rtl.min.css.9c513f8c92e8.map", "assetz/vendor/bootstrap/css/bootstrap-reboot.css": "assetz/vendor/bootstrap/css/bootstrap-reboot.6f135d88e922.css", "assetz/vendor/bootstrap/css/bootstrap-utilities.min.css": "assetz/vendor/bootstrap/css/bootstrap-utilities.min.a35a29ce7d65.css", "assetz/vendor/bootstrap/css/bootstrap-grid.rtl.css": "assetz/vendor/bootstrap/css/bootstrap-grid.rtl.0e054821afd8.css", "assetz/vendor/bootstrap/css/bootstrap-grid.rtl.min.css": "assetz/vendor/bootstrap/css/bootstrap-grid.rtl.min.b1d4aae85921.css", "assetz/vendor/bootstrap/css/bootstrap-utilities.css": "assetz/vendor/bootstrap/css/bootstrap-utilities.ce630c48b6c7.css", "assetz/vendor/bootstrap/css/bootstrap.rtl.css.map": "assetz/vendor/bootstrap/css/bootstrap.rtl.css.5552892ca514.map", "assetz/vendor/bootstrap/css/bootstrap.min.css": "assetz/vendor/bootstrap/css/bootstrap.min.8880ffcc419e.css", "assetz/vendor/bootstrap/css/bootstrap-grid.rtl.css.map": "assetz/vendor/bootstrap/css/bootstrap-grid.rtl.css.450e176760f4.map", "assetz/vendor/bootstrap/css/bootstrap-utilities.rtl.min.css.map": "assetz/vendor/bootstrap/css/bootstrap-utilities.rtl.min.css.178606d53e67.map", "assetz/vendor/bootstrap/css/bootstrap-reboot.min.css.map": "assetz/vendor/bootstrap/css/bootstrap-reboot.min.css.9145e8bfaab5.map", "assetz/vendor/bootstrap/css/bootstrap-grid.min.css": "assetz/vendor/bootstrap/css/bootstrap-grid.min.e7454e3d83e7.css", "assetz/vendor/bootstrap/css/bootstrap-utilities.rtl.css": "assetz/vendor/bootstrap/css/bootstrap-utilities.rtl.7c8346b31832.css", "assetz/vendor/bootstrap/css/bootstrap-utilities.rtl.min.css": "assetz/vendor/bootstrap/css/bootstrap-utilities.rtl.min.048af6e1c02b.css", "assetz/vendor/bootstrap/css/bootstrap-utilities.rtl.css.map": "assetz/vendor/bootstrap/css/bootstrap-utilities.rtl.css.4ad7c88ffe2b.map", "assetz/vendor/bootstrap/css/bootstrap-utilities.css.map": "assetz/vendor/bootstrap/css/bootstrap-utilities.css.7b8e4e64b530.map", "assetz/vendor/bootstrap/css/bootstrap-grid.min.css.map": "assetz/vendor/bootstrap/css/bootstrap-grid.min.css.7f3903bb8598.map", "assetz/vendor/bootstrap/css/bootstrap.css": "assetz/vendor/bootstrap/css/bootstrap.f6e962ab807e.css", "assetz/vendor/bootstrap/css/bootstrap-reboot.rtl.css.map": "assetz/vendor/bootstrap/css/bootstrap-reboot.rtl.css.35a012269edc.map", "assetz/vendor/bootstrap/css/bootstrap-reboot.rtl.css": "assetz/vendor/bootstrap/css/bootstrap-reboot.rtl.dcae73d819a3.css", "assetz/vendor/bootstrap/css/bootstrap.rtl.min.css": "assetz/vendor/bootstrap/css/bootstrap.rtl.min.6d7fa20ffe03.css", "assetz/vendor/bootstrap/css/bootstrap.rtl.css": "assetz/vendor/bootstrap/css/bootstrap.rtl.d93015b59c22.css", "assetz/vendor/bootstrap/css/bootstrap.rtl.min.css.map": "assetz/vendor/bootstrap/css/bootstrap.rtl.min.css.a346b256320f.map", "assetz/vendor/bootstrap/css/bootstrap-utilities.min.css.map": "assetz/vendor/bootstrap/css/bootstrap-utilities.min.css.e4d4e76abc6f.map", "assetz/vendor/bootstrap/css/bootstrap-grid.css": "assetz/vendor/bootstrap/css/bootstrap-grid.cf899c195cc8.css", "assetz/vendor/boxicons/css/boxicons.css": "assetz/vendor/boxicons/css/boxicons.f1d97f2f1377.css", "assetz/vendor/boxicons/css/transformations.css": "assetz/vendor/boxicons/css/transformations.d5afab8d6fa0.css", "assetz/vendor/boxicons/css/animations.css": "assetz/vendor/boxicons/css/animations.2c0319e25c5c.css", "assetz/vendor/boxicons/css/boxicons.min.css": "assetz/vendor/boxicons/css/boxicons.min.a0e66e2b913f.css", "assetz/vendor/boxicons/fonts/boxicons.eot": "assetz/vendor/boxicons/fonts/boxicons.342c527555cf.eot", "assetz/vendor/boxicons/fonts/boxicons.woff": "assetz/vendor/boxicons/fonts/boxicons.86708f260a76.woff", "assetz/vendor/boxicons/fonts/boxicons.ttf": "assetz/vendor/boxicons/fonts/boxicons.8829e87f7fef.ttf", "assetz/vendor/boxicons/fonts/boxicons.svg": "assetz/vendor/boxicons/fonts/boxicons.dad92ba1a4ee.svg", "assetz/vendor/boxicons/fonts/boxicons.woff2": "assetz/vendor/boxicons/fonts/boxicons.b5e3cc0c6aa6.woff2", "assetz/vendor/bootstrap-icons/fonts/bootstrap-icons.woff": "assetz/vendor/bootstrap-icons/fonts/bootstrap-icons.7fb23f3b56a8.woff", "assetz/vendor/bootstrap-icons/fonts/bootstrap-icons.woff2": "assetz/vendor/bootstrap-icons/fonts/bootstrap-icons.e07b538aa51b.woff2", "assetz/css/icofont/fonts/icofont.woff": "assetz/css/icofont/fonts/icofont.f6ab04aed30a.woff", "assetz/css/icofont/fonts/icofont.svg": "assetz/css/icofont/fonts/icofont.47d8c4d6ee7c.svg", "assetz/css/icofont/fonts/icofont.woff2": "assetz/css/icofont/fonts/icofont.50a4ab76e700.woff2", "assetz/css/icofont/fonts/icofont.eot": "assetz/css/icofont/fonts/icofont.20e606bb2a29.eot", "assetz/css/icofont/fonts/icofont.ttf": "assetz/css/icofont/fonts/icofont.22304f677719.ttf", "admin/js/admin/DateTimeShortcuts.js": "admin/js/admin/DateTimeShortcuts.5548f99471bf.js", "admin/js/admin/RelatedObjectLookups.js": "admin/js/admin/RelatedObjectLookups.b4d76b6aaf0b.js", "admin/img/gis/move_vertex_on.svg": "admin/img/gis/move_vertex_on.0047eba25b67.svg", "admin/img/gis/move_vertex_off.svg": "admin/img/gis/move_vertex_off.7a23bf31ef8a.svg", "assets/vendors/progressbar.js/progressbar.min.js": "assets/vendors/progressbar.js/progressbar.min.013916ab6148.js", "assets/vendors/select2/select2.min.css": "assets/vendors/select2/select2.min.9f54e6414f87.css", "assets/vendors/select2/select2.min.js": "assets/vendors/select2/select2.min.0f64f3a3a0c6.js", "assets/vendors/js/bootstrap.min.js.map": "assets/vendors/js/bootstrap.min.js.e7faa89b97be.map", "assets/vendors/js/vendor.bundle.base.js": "assets/vendors/js/vendor.bundle.base.47e3d9d30028.js", "assets/vendors/select2-bootstrap-theme/select2-bootstrap.min.css": "assets/vendors/select2-bootstrap-theme/select2-bootstrap.min.b8ec8e1bea84.css", "assets/vendors/chart.js/Chart.min.js": "assets/vendors/chart.js/Chart.min.b5c2301eb158.js", "assets/vendors/owl-carousel-2/owl.theme.default.min.css": "assets/vendors/owl-carousel-2/owl.theme.default.min.594b81805a98.css", "assets/vendors/owl-carousel-2/owl.carousel.min.js": "assets/vendors/owl-carousel-2/owl.carousel.min.f416f9031fef.js", "assets/vendors/owl-carousel-2/owl.carousel.min.css": "assets/vendors/owl-carousel-2/owl.carousel.min.761bea69e4eb.css", "assets/vendors/owl-carousel-2/owl.video.play.png": "assets/vendors/owl-carousel-2/owl.video.play.4a37f8008959.png", "assets/vendors/css/vendor.bundle.base.css": "assets/vendors/css/vendor.bundle.base.271c6cf8bc08.css", "assets/vendors/codemirror/codemirror.css": "assets/vendors/codemirror/codemirror.fc217d502b05.css", "assets/vendors/codemirror/shell.js": "assets/vendors/codemirror/shell.3491c0f88da7.js", "assets/vendors/codemirror/codemirror.js": "assets/vendors/codemirror/codemirror.a92bb59eba91.js", "assets/vendors/codemirror/javascript.js": "assets/vendors/codemirror/javascript.2b20ebbc6376.js", "assets/vendors/codemirror/ambiance.css": "assets/vendors/codemirror/ambiance.8996c0efee66.css", "assets/vendors/typeahead.js/typeahead.bundle.min.js": "assets/vendors/typeahead.js/typeahead.bundle.min.cc8f40838480.js", "assets/vendors/jvectormap/jquery-jvectormap.css": "assets/vendors/jvectormap/jquery-jvectormap.bcce7128a1b0.css", "assets/vendors/jvectormap/jquery-jvectormap-world-mill-en.js": "assets/vendors/jvectormap/jquery-jvectormap-world-mill-en.9b13fed64f6d.js", "assets/vendors/jvectormap/jquery-jvectormap.min.js": "assets/vendors/jvectormap/jquery-jvectormap.min.5bc515549418.js", "assets/vendors/pwstabs/jquery.pwstabs.min.css": "assets/vendors/pwstabs/jquery.pwstabs.min.95fc3cd1eade.css", "assets/vendors/pwstabs/jquery.pwstabs.min.js": "assets/vendors/pwstabs/jquery.pwstabs.min.34bf486ef33d.js", "assets/css/maps/style.css.map": "assets/css/maps/style.css.aceab528a9a8.map", "assets/fonts/Rubik/Rubik-Black.ttf": "assets/fonts/Rubik/Rubik-Black.fba2019b0b09.ttf", "assets/fonts/Rubik/Rubik-Light.ttf": "assets/fonts/Rubik/Rubik-Light.7a06846baf7f.ttf", "assets/fonts/Rubik/Rubik-Medium.ttf": "assets/fonts/Rubik/Rubik-Medium.c87313aa86b7.ttf", "assets/fonts/Rubik/Rubik-Regular.ttf": "assets/fonts/Rubik/Rubik-Regular.b3d0902b533f.ttf", "assets/fonts/Rubik/Rubik-Bold.ttf": "assets/fonts/Rubik/Rubik-Bold.9a6fb6f5cd3a.ttf", "assets/fonts/Assistant/Assistant-Bold.eot": "assets/fonts/Assistant/Assistant-Bold.8bcc276fa42f.eot", "assets/fonts/Assistant/Assistant-Regular.woff": "assets/fonts/Assistant/Assistant-Regular.a3624cce786e.woff", "assets/fonts/Assistant/Assistant-Bold.ttf": "assets/fonts/Assistant/Assistant-Bold.48b43ed47862.ttf", "assets/fonts/Assistant/Assistant-ExtraLight.woff": "assets/fonts/Assistant/Assistant-ExtraLight.208eab533da3.woff", "assets/fonts/Assistant/Assistant-ExtraBold.woff": "assets/fonts/Assistant/Assistant-ExtraBold.68b4965b2fdc.woff", "assets/fonts/Assistant/Assistant-Light.eot": "assets/fonts/Assistant/Assistant-Light.9aad344c7f21.eot", "assets/fonts/Assistant/Assistant-SemiBold.woff": "assets/fonts/Assistant/Assistant-SemiBold.2f9e7376e048.woff", "assets/fonts/Assistant/Assistant-Regular.eot": "assets/fonts/Assistant/Assistant-Regular.799f33452110.eot", "assets/fonts/Assistant/Assistant-Light.ttf": "assets/fonts/Assistant/Assistant-Light.83bbee90f219.ttf", "assets/fonts/Assistant/Assistant-ExtraLight.eot": "assets/fonts/Assistant/Assistant-ExtraLight.2a0f6e10061f.eot", "assets/fonts/Assistant/Assistant-Light.woff": "assets/fonts/Assistant/Assistant-Light.ebfe4d323bc1.woff", "assets/fonts/Assistant/Assistant-SemiBold.ttf": "assets/fonts/Assistant/Assistant-SemiBold.c2c155eb6873.ttf", "assets/fonts/Assistant/Assistant-Light.woff2": "assets/fonts/Assistant/Assistant-Light.699a6b5f08ba.woff2", "assets/fonts/Assistant/Assistant-SemiBold.woff2": "assets/fonts/Assistant/Assistant-SemiBold.994dff843742.woff2", "assets/fonts/Assistant/Assistant-Bold.woff2": "assets/fonts/Assistant/Assistant-Bold.5c65779edeaa.woff2", "assets/fonts/Assistant/Assistant-ExtraBold.woff2": "assets/fonts/Assistant/Assistant-ExtraBold.a1134ecdbb7f.woff2", "assets/fonts/Assistant/Assistant-Bold.woff": "assets/fonts/Assistant/Assistant-Bold.02c5fc672225.woff", "assets/fonts/Assistant/Assistant-ExtraBold.eot": "assets/fonts/Assistant/Assistant-ExtraBold.88eac8f8d1fe.eot", "assets/fonts/Assistant/Assistant-ExtraBold.ttf": "assets/fonts/Assistant/Assistant-ExtraBold.da6afa962cea.ttf", "assets/fonts/Assistant/Assistant-SemiBold.eot": "assets/fonts/Assistant/Assistant-SemiBold.9ffa6ab93d30.eot", "assets/fonts/Assistant/Assistant-ExtraLight.ttf": "assets/fonts/Assistant/Assistant-ExtraLight.eaa6b90373d5.ttf", "assets/fonts/Assistant/Assistant-ExtraLight.woff2": "assets/fonts/Assistant/Assistant-ExtraLight.74895b139cb5.woff2", "assets/fonts/Assistant/Assistant-Regular.ttf": "assets/fonts/Assistant/Assistant-Regular.ffc48999dd1c.ttf", "assets/fonts/Assistant/Assistant-Regular.woff2": "assets/fonts/Assistant/Assistant-Regular.e8e38a9d0250.woff2", "assetz/vendor/purecounter/purecounter.js": "assetz/vendor/purecounter/purecounter.50d43f946b93.js", "assetz/vendor/waypoints/noframework.waypoints.js": "assetz/vendor/waypoints/noframework.waypoints.8c601d5f892e.js", "assetz/vendor/animate.css/animate.compat.css": "assetz/vendor/animate.css/animate.compat.9bb18ac93ea3.css", "assetz/vendor/animate.css/animate.css": "assetz/vendor/animate.css/animate.cf2741a3a7ea.css", "assetz/vendor/animate.css/animate.min.css": "assetz/vendor/animate.css/animate.min.c0be8e53226a.css", "assetz/vendor/swiper/swiper-bundle.min.css": "assetz/vendor/swiper/swiper-bundle.min.b2b598cf96cd.css", "assetz/vendor/swiper/swiper-bundle.min.js": "assetz/vendor/swiper/swiper-bundle.min.f65b2f51f3a1.js", "assetz/vendor/php-email-form/validate.js": "assetz/vendor/php-email-form/validate.2e42d48f58bd.js", "assetz/vendor/bootstrap-icons/bootstrap-icons.json": "assetz/vendor/bootstrap-icons/bootstrap-icons.9c05cc16dfd1.json", "assetz/vendor/bootstrap-icons/bootstrap-icons.css": "assetz/vendor/bootstrap-icons/bootstrap-icons.22c8288b0d8f.css", "assetz/vendor/bootstrap-icons/index.html": "assetz/vendor/bootstrap-icons/index.5bd0231cfd71.html", "assetz/vendor/aos/aos.css": "assetz/vendor/aos/aos.847da8fca806.css", "assetz/vendor/aos/aos.js": "assetz/vendor/aos/aos.d3718e34eeb0.js", "assetz/vendor/isotope-layout/isotope.pkgd.js": "assetz/vendor/isotope-layout/isotope.pkgd.8896e082b3fa.js", "assetz/vendor/isotope-layout/isotope.pkgd.min.js": "assetz/vendor/isotope-layout/isotope.pkgd.min.2afcff647ed2.js", "assetz/css/icofont/icofont.min.css": "assetz/css/icofont/icofont.min.134b8dae50ca.css", "assetz/css/icofont/demo.html": "assetz/css/icofont/demo.0f315e43223f.html", "assetz/css/icofont/icofont.css": "assetz/css/icofont/icofont.fcca87a2d3f4.css", "markdownx/admin/css/markdownx.min.css": "markdownx/admin/css/markdownx.min.cc0cbd4d28bb.css", "markdownx/admin/css/markdownx.css": "markdownx/admin/css/markdownx.18206e3a09bc.css", "admin/js/prepopulate_init.js": "admin/js/prepopulate_init.e056047b7a7e.js", "admin/js/urlify.js": "admin/js/urlify.25cc3eac8123.js", "admin/js/cancel.js": "admin/js/cancel.ecc4c5ca7b32.js", "admin/js/popup_response.js": "admin/js/popup_response.c6cc78ea5551.js", "admin/js/jquery.init.js": "admin/js/jquery.init.b7781a0897fc.js", "admin/js/actions.js": "admin/js/actions.a6d23e8853fd.js", "admin/js/calendar.js": "admin/js/calendar.f8a5d055eb33.js", "admin/js/SelectFilter2.js": "admin/js/SelectFilter2.d250dcb52a9a.js", "admin/js/SelectBox.js": "admin/js/SelectBox.8161741c7647.js", "admin/js/nav_sidebar.js": "admin/js/nav_sidebar.7605597ddf52.js", "admin/js/core.js": "admin/js/core.ccd84108ec57.js", "admin/js/inlines.js": "admin/js/inlines.7596b7fd289e.js", "admin/js/change_form.js": "admin/js/change_form.9d8ca4f96b75.js", "admin/js/autocomplete.js": "admin/js/autocomplete.b6b77d0e5906.js", "admin/js/collapse.js": "admin/js/collapse.f84e7410290f.js", "admin/js/prepopulate.js": "admin/js/prepopulate.bd2361dfd64d.js", "admin/img/icon-unknown-alt.svg": "admin/img/icon-unknown-alt.81536e128bb6.svg", "admin/img/icon-unknown.svg": "admin/img/icon-unknown.a18cb4398978.svg", "admin/img/README.txt": "admin/img/README.a70711a38d87.txt", "admin/img/search.svg": "admin/img/search.7cf54ff789c6.svg", "admin/img/icon-deletelink.svg": "admin/img/icon-deletelink.564ef9dc3854.svg", "admin/img/icon-addlink.svg": "admin/img/icon-addlink.d519b3bab011.svg", "admin/img/selector-icons.svg": "admin/img/selector-icons.b4555096cea2.svg", "admin/img/calendar-icons.svg": "admin/img/calendar-icons.39b290681a8b.svg", "admin/img/icon-no.svg": "admin/img/icon-no.439e821418cd.svg", "admin/img/LICENSE": "admin/img/LICENSE.2c54f4e1ca1c", "admin/img/sorting-icons.svg": "admin/img/sorting-icons.3a097b59f104.svg", "admin/img/icon-calendar.svg": "admin/img/icon-calendar.ac7aea671bea.svg", "admin/img/icon-viewlink.svg": "admin/img/icon-viewlink.41eb31f7826e.svg", "admin/img/icon-changelink.svg": "admin/img/icon-changelink.18d2fd706348.svg", "admin/img/icon-clock.svg": "admin/img/icon-clock.e1d4dfac3f2b.svg", "admin/img/icon-yes.svg": "admin/img/icon-yes.d2f9f035226a.svg", "admin/img/tooltag-add.svg": "admin/img/tooltag-add.e59d620a9742.svg", "admin/img/icon-alert.svg": "admin/img/icon-alert.034cc7d8a67f.svg", "admin/img/inline-delete.svg": "admin/img/inline-delete.fec1b761f254.svg", "admin/img/tooltag-arrowright.svg": "admin/img/tooltag-arrowright.bbfb788a849e.svg", "admin/css/changelists.css": "admin/css/changelists.c70d77c47e69.css", "admin/css/responsive_rtl.css": "admin/css/responsive_rtl.e13ae754cceb.css", "admin/css/base.css": "admin/css/base.1f418065fc2c.css", "admin/css/widgets.css": "admin/css/widgets.694d845b2cb1.css", "admin/css/autocomplete.css": "admin/css/autocomplete.4a81fc4242d0.css", "admin/css/forms.css": "admin/css/forms.1d89ec6432f5.css", "admin/css/responsive.css": "admin/css/responsive.b128bdf0edef.css", "admin/css/dashboard.css": "admin/css/dashboard.be83f13e4369.css", "admin/css/login.css": "admin/css/login.c35adf41bb6e.css", "admin/css/fonts.css": "admin/css/fonts.168bab448fee.css", "admin/css/rtl.css": "admin/css/rtl.4bc23eb90919.css", "admin/css/nav_sidebar.css": "admin/css/nav_sidebar.0fd434145f4d.css", "admin/fonts/README.txt": "admin/fonts/README.ab99e6b541ea.txt", "admin/fonts/Roboto-Regular-webfont.woff": "admin/fonts/Roboto-Regular-webfont.35b07eb2f871.woff", "admin/fonts/Roboto-Bold-webfont.woff": "admin/fonts/Roboto-Bold-webfont.50d75e48e0a3.woff", "admin/fonts/Roboto-Light-webfont.woff": "admin/fonts/Roboto-Light-webfont.c73eb1ceba33.woff", "admin/fonts/LICENSE.txt": "admin/fonts/LICENSE.d273d63619c9.txt", "assets/js/popover.js": "assets/js/popover.a01b9c0e9355.js", "assets/js/profile-demo.js": "assets/js/profile-demo.13713322babd.js", "assets/js/dropify.js": "assets/js/dropify.22f7782a105b.js", "assets/js/desktop-notification.js": "assets/js/desktop-notification.019b2bd9ffb8.js", "assets/js/inputmask.js": "assets/js/inputmask.e3023bff68b1.js", "assets/js/data-table.js": "assets/js/data-table.ee8707d52d13.js", "assets/js/context-menu.js": "assets/js/context-menu.7e17d62bbe33.js", "assets/js/tooltips.js": "assets/js/tooltips.9f2f909256e0.js", "assets/js/modal-demo.js": "assets/js/modal-demo.911be417bac8.js", "assets/js/light-gallery.js": "assets/js/light-gallery.f98badfb405c.js", "assets/js/google-maps.js": "assets/js/google-maps.f96f2610a87e.js", "assets/js/x-editable.js": "assets/js/x-editable.ac1e7c752be0.js", "assets/js/form-repeater.js": "assets/js/form-repeater.a64dadec02fc.js", "assets/js/clipboard.js": "assets/js/clipboard.c8a2c741aaad.js", "assets/js/js-grid.js": "assets/js/js-grid.b4bb84137104.js", "assets/js/iCheck.js": "assets/js/iCheck.fdd73bed94cb.js", "assets/js/paginate.js": "assets/js/paginate.3b79bb340e9e.js", "assets/js/morris.js": "assets/js/morris.46a86cffa7bb.js", "assets/js/bootstrap-table.js": "assets/js/bootstrap-table.31b3be1c34a9.js", "assets/js/form-addons.js": "assets/js/form-addons.9a21592de382.js", "assets/js/ace.js": "assets/js/ace.120cc2ddd73d.js", "assets/js/codeEditor.js": "assets/js/codeEditor.ab34b27715be.js", "assets/js/dashboard.js": "assets/js/dashboard.44b642662613.js", "assets/js/cropper.js": "assets/js/cropper.039ee3fd51d0.js", "assets/js/codemirror.js": "assets/js/codemirror.e455fd7263b7.js", "assets/js/hoverable-collapse.js": "assets/js/hoverable-collapse.9e32768c8ba8.js", "assets/js/mapael_example_2.js": "assets/js/mapael_example_2.231db2ee7e14.js", "assets/js/db.js": "assets/js/db.f788d5a8475c.js", "assets/js/owl-carousel.js": "assets/js/owl-carousel.164415bc77ba.js", "assets/js/tight-grid.js": "assets/js/tight-grid.2e8e08f24046.js", "assets/js/calendar.js": "assets/js/calendar.454fadfa5cd8.js", "assets/js/jq.tablesort.js": "assets/js/jq.tablesort.9529a0c44d71.js", "assets/js/listify.js": "assets/js/listify.ef1185811921.js", "assets/js/select2.js": "assets/js/select2.ec9e22f66e55.js", "assets/js/mapael_example_1.js": "assets/js/mapael_example_1.7851f2c3c6ad.js", "assets/js/misc.js": "assets/js/misc.692e9599b60f.js", "assets/js/wizard.js": "assets/js/wizard.0363e9ae3a91.js", "assets/js/flot-chart.js": "assets/js/flot-chart.e92d918c6e35.js", "assets/js/widgets.js": "assets/js/widgets.3d9372268123.js", "assets/js/toastDemo.js": "assets/js/toastDemo.cec09db9b333.js", "assets/js/reg-validator.js": "assets/js/reg-validator.d41d8cd98f00.js", "assets/js/editorDemo.js": "assets/js/editorDemo.7824f02fc5a7.js", "assets/js/progress-bar.js": "assets/js/progress-bar.69d90c748632.js", "assets/js/tablesorter.js": "assets/js/tablesorter.b4a9b5aa8bea.js", "assets/js/dropzone.js": "assets/js/dropzone.edda3a9c06dc.js", "assets/js/chart.js": "assets/js/chart.992783f74b70.js", "assets/js/off-canvas.js": "assets/js/off-canvas.96bd27f77418.js", "assets/js/todolist.js": "assets/js/todolist.1d9d22bb0cb5.js", "assets/js/dragula.js": "assets/js/dragula.cc21b08689dc.js", "assets/js/jquery-file-upload.js": "assets/js/jquery-file-upload.efb4a0e2b703.js", "assets/js/mapael.js": "assets/js/mapael.fb6095def438.js", "assets/js/avgrund.js": "assets/js/avgrund.2feec6425851.js", "assets/js/just-gage.js": "assets/js/just-gage.93401d0b4bba.js", "assets/js/formpickers.js": "assets/js/formpickers.0d1b3f98fcb0.js", "assets/js/form-validation.js": "assets/js/form-validation.bff2a8d6d510.js", "assets/js/rickshaw.js": "assets/js/rickshaw.13e3a9595652.js", "assets/js/bt-maxLength.js": "assets/js/bt-maxLength.4c46a31127e7.js", "assets/js/c3.js": "assets/js/c3.51b5f8e3a1c9.js", "assets/js/jquery.js": "assets/js/jquery.5968aeefb947.js", "assets/js/tabs.js": "assets/js/tabs.54b9a9d79337.js", "assets/js/ion-range-slider.js": "assets/js/ion-range-slider.7fe57ad6b5b8.js", "assets/js/google-charts.js": "assets/js/google-charts.b23de81fff86.js", "assets/js/typeahead.js": "assets/js/typeahead.aa9e5a33ce4c.js", "assets/js/sparkline.js": "assets/js/sparkline.56a0e147ece7.js", "assets/js/chartist.js": "assets/js/chartist.b830e623d5a8.js", "assets/js/no-ui-slider.js": "assets/js/no-ui-slider.8a100d0190b4.js", "assets/js/maps.js": "assets/js/maps.95125887de0a.js", "assets/js/alerts.js": "assets/js/alerts.8ca0f6befe80.js", "assets/js/circle-progress.js": "assets/js/circle-progress.576dcd4f2c02.js", "assets/js/file-upload.js": "assets/js/file-upload.030f91b039d0.js", "assets/js/settings.js": "assets/js/settings.da7cc9e12269.js", "assets/css/rtl.css": "assets/css/rtl.fe25838046fc.css", "assetz/js/main.js": "assetz/js/main.a1b363991754.js", "assetz/img/anony-avatar.png": "assetz/img/anony-avatar.e99ddb913790.png", "assetz/img/features-4.svg": "assetz/img/features-4.a961f4486cba.svg", "assetz/img/features-3.svg": "assetz/img/features-3.cf0b6b88896b.svg", "assetz/img/hero-bg.jpg": "assetz/img/hero-bg.c5daca9a0e33.jpg", "assetz/img/features-2.svg": "assetz/img/features-2.529facd4cee1.svg", "assetz/img/features-1.svg": "assetz/img/features-1.52980d42775d.svg", "assetz/css/style.css": "assetz/css/style.b6a05936221a.css", "markdownx/js/markdownx.js": "markdownx/js/markdownx.dfbae5de3e3b.js", "markdownx/js/markdownx.min.js": "markdownx/js/markdownx.min.e91249b83c96.js", "assets/chart.js": "assets/chart.ec58f74e37c6.js", "js/jquery.fileupload-process.js": "js/jquery.fileupload-process.840f65232eaf.js", "js/canvas-to-blob.min.js": "js/canvas-to-blob.min.33ecbe6885ad.js", "js/jquery.fileupload-image.js": "js/jquery.fileupload-image.7c40367b00f7.js", "js/load-image.all.min.js": "js/load-image.all.min.c4cdadc311ce.js", "js/jquery.fileupload.js": "js/jquery.fileupload.4bfd85460689.js", "js/jquery.cloudinary.js": "js/jquery.cloudinary.0d492c6cd335.js", "js/jquery.ui.widget.js": "js/jquery.ui.widget.3d0f0f5ca5d8.js", "js/jquery.iframe-transport.js": "js/jquery.iframe-transport.f371e8d9f573.js", "js/jquery.fileupload-validate.js": "js/jquery.fileupload-validate.a144e6149c89.js", "html/cloudinary_cors.html": "html/cloudinary_cors.31bb92a42818.html"}, "version": "1.0"}